<?xml version="1.0"?>
<MethodSetup Method="DL::DNN_GPU1">
  <GeneralInfo>
    <Info name="TMVA Release" value="4.2.1 [262657]"/>
    <Info name="ROOT Release" value="6.26/06 [399878]"/>
    <Info name="Creator" value="markm"/>
    <Info name="Date" value="Tue Nov  1 20:45:31 2022"/>
    <Info name="Host" value="Linux kgizdov 5.19.4-arch1-1 #1 SMP PREEMPT_DYNAMIC Thu, 25 Aug 2022 17:31:12 +0000 x86_64 GNU/Linux"/>
    <Info name="Dir" value="/home/markm/code/EAL"/>
    <Info name="Training events" value="176323"/>
    <Info name="TrainingTime" value="2.04877692e+02"/>
    <Info name="AnalysisType" value="Classification"/>
  </GeneralInfo>
  <Options>
    <Option name="V" modified="Yes">True</Option>
    <Option name="VerbosityLevel" modified="No">Verbose</Option>
    <Option name="VarTransform" modified="Yes">N</Option>
    <Option name="H" modified="Yes">False</Option>
    <Option name="CreateMVAPdfs" modified="No">False</Option>
    <Option name="IgnoreNegWeightsInTraining" modified="No">False</Option>
    <Option name="InputLayout" modified="No">0|0|0</Option>
    <Option name="BatchLayout" modified="No">0|0|0</Option>
    <Option name="Layout" modified="Yes">RELU|256,LINEAR</Option>
    <Option name="ErrorStrategy" modified="Yes">CROSSENTROPY</Option>
    <Option name="WeightInitialization" modified="Yes">XAVIERUNIFORM</Option>
    <Option name="RandomSeed" modified="No">0</Option>
    <Option name="ValidationSize" modified="No">20%</Option>
    <Option name="Architecture" modified="Yes">GPU</Option>
    <Option name="TrainingStrategy" modified="No">LearningRate=1e-3,Momentum=0.0,ConvergenceSteps=100,MaxEpochs=2000,Optimizer=ADAM,BatchSize=30,TestRepetitions=1,WeightDecay=0.0,Regularization=None,DropConfig=0.0</Option>
  </Options>
  <Variables NVar="15">
    <Variable VarIndex="0" Expression="bos_PuppiAK8_eta" Label="bos_PuppiAK8_eta" Title="bos_PuppiAK8_eta" Unit="" Internal="bos_PuppiAK8_eta" Type="F" Min="-2.39990234e+00" Max="2.39990234e+00"/>
    <Variable VarIndex="1" Expression="bos_PuppiAK8_m_sd0_corr" Label="bos_PuppiAK8_m_sd0_corr" Title="bos_PuppiAK8_m_sd0_corr" Unit="" Internal="bos_PuppiAK8_m_sd0_corr" Type="F" Min="6.50625000e+01" Max="1.04937500e+02"/>
    <Variable VarIndex="2" Expression="bos_PuppiAK8_tau2tau1" Label="bos_PuppiAK8_tau2tau1" Title="bos_PuppiAK8_tau2tau1" Unit="" Internal="bos_PuppiAK8_tau2tau1" Type="F" Min="1.40449442e-02" Max="5.49973011e-01"/>
    <Variable VarIndex="3" Expression="dibos_m" Label="dibos_m" Title="dibos_m" Unit="" Internal="dibos_m" Type="F" Min="1.28920578e+02" Max="5.91505127e+03"/>
    <Variable VarIndex="4" Expression="lep1_eta" Label="lep1_eta" Title="lep1_eta" Unit="" Internal="lep1_eta" Type="F" Min="-2.50000000e+00" Max="2.49902344e+00"/>
    <Variable VarIndex="5" Expression="nJet30f" Label="nJet30f" Title="nJet30f" Unit="" Internal="nJet30f" Type="F" Min="2.00000000e+00" Max="1.30000000e+01"/>
    <Variable VarIndex="6" Expression="vbf1_AK4_eta" Label="vbf1_AK4_eta" Title="vbf1_AK4_eta" Unit="" Internal="vbf1_AK4_eta" Type="F" Min="-4.66796875e+00" Max="4.65820312e+00"/>
    <Variable VarIndex="7" Expression="vbf1_AK4_qgid" Label="vbf1_AK4_qgid" Title="vbf1_AK4_qgid" Unit="" Internal="vbf1_AK4_qgid" Type="F" Min="3.32947820e-08" Max="1.00000000e+00"/>
    <Variable VarIndex="8" Expression="vbf2_AK4_eta" Label="vbf2_AK4_eta" Title="vbf2_AK4_eta" Unit="" Internal="vbf2_AK4_eta" Type="F" Min="-4.68457031e+00" Max="4.69042969e+00"/>
    <Variable VarIndex="9" Expression="vbf2_AK4_qgid" Label="vbf2_AK4_qgid" Title="vbf2_AK4_qgid" Unit="" Internal="vbf2_AK4_qgid" Type="F" Min="1.21165067e-06" Max="1.00000000e+00"/>
    <Variable VarIndex="10" Expression="vbf_deta" Label="vbf_deta" Title="vbf_deta" Unit="" Internal="vbf_deta" Type="F" Min="2.50012207e+00" Max="8.85058594e+00"/>
    <Variable VarIndex="11" Expression="vbf_eta" Label="vbf_eta" Title="vbf_eta" Unit="" Internal="vbf_eta" Type="F" Min="-8.29465294e+00" Max="7.37775660e+00"/>
    <Variable VarIndex="12" Expression="vbf_m" Label="vbf_m" Title="vbf_m" Unit="" Internal="vbf_m" Type="F" Min="5.00000275e+02" Max="8.48247266e+03"/>
    <Variable VarIndex="13" Expression="zeppHad" Label="zeppHad" Title="zeppHad" Unit="" Internal="zeppHad" Type="F" Min="-3.21459961e+00" Max="3.27465820e+00"/>
    <Variable VarIndex="14" Expression="zeppLep" Label="zeppLep" Title="zeppLep" Unit="" Internal="zeppLep" Type="F" Min="-3.48477864e+00" Max="3.39856219e+00"/>
  </Variables>
  <Spectators NSpec="60">
    <Spectator SpecIndex="0" Expression="AntiIsoInt" Label="AntiIsoInt" Title="I" Unit="" Internal="AntiIsoInt" Type="F" Min="0.00000000e+00" Max="0.00000000e+00"/>
    <Spectator SpecIndex="1" Expression="bos_AK4AK4_eta" Label="bos_AK4AK4_eta" Title="F" Unit="" Internal="bos_AK4AK4_eta" Type="F" Min="-9.99000000e+02" Max="-9.99000000e+02"/>
    <Spectator SpecIndex="2" Expression="bos_AK4AK4_m" Label="bos_AK4AK4_m" Title="F" Unit="" Internal="bos_AK4AK4_m" Type="F" Min="-9.99000000e+02" Max="-9.99000000e+02"/>
    <Spectator SpecIndex="3" Expression="bos_AK4AK4_pt" Label="bos_AK4AK4_pt" Title="F" Unit="" Internal="bos_AK4AK4_pt" Type="F" Min="-9.99000000e+02" Max="-9.99000000e+02"/>
    <Spectator SpecIndex="4" Expression="bosCent" Label="bosCent" Title="F" Unit="" Internal="bosCent" Type="F" Min="1.11022302e-16" Max="4.13032436e+00"/>
    <Spectator SpecIndex="5" Expression="bos_j1_AK4_eta" Label="bos_j1_AK4_eta" Title="F" Unit="" Internal="bos_j1_AK4_eta" Type="F" Min="-9.99000000e+02" Max="-9.99000000e+02"/>
    <Spectator SpecIndex="6" Expression="bos_j1_AK4_pt" Label="bos_j1_AK4_pt" Title="F" Unit="" Internal="bos_j1_AK4_pt" Type="F" Min="-9.99000000e+02" Max="-9.99000000e+02"/>
    <Spectator SpecIndex="7" Expression="bos_j2_AK4_eta" Label="bos_j2_AK4_eta" Title="F" Unit="" Internal="bos_j2_AK4_eta" Type="F" Min="-9.99000000e+02" Max="-9.99000000e+02"/>
    <Spectator SpecIndex="8" Expression="bos_j2_AK4_pt" Label="bos_j2_AK4_pt" Title="F" Unit="" Internal="bos_j2_AK4_pt" Type="F" Min="-9.99000000e+02" Max="-9.99000000e+02"/>
    <Spectator SpecIndex="9" Expression="bos_PuppiAK8_m_sd0" Label="bos_PuppiAK8_m_sd0" Title="F" Unit="" Internal="bos_PuppiAK8_m_sd0" Type="F" Min="6.50625000e+01" Max="1.04937500e+02"/>
    <Spectator SpecIndex="10" Expression="bos_PuppiAK8_phi" Label="bos_PuppiAK8_phi" Title="F" Unit="" Internal="bos_PuppiAK8_phi" Type="F" Min="-3.14160156e+00" Max="3.14160156e+00"/>
    <Spectator SpecIndex="11" Expression="bos_PuppiAK8_pt" Label="bos_PuppiAK8_pt" Title="F" Unit="" Internal="bos_PuppiAK8_pt" Type="F" Min="2.00125000e+02" Max="2.85600000e+03"/>
    <Spectator SpecIndex="12" Expression="btagWeight_loose" Label="btagWeight_loose" Title="F" Unit="" Internal="btagWeight_loose" Type="F" Min="4.47307110e-01" Max="2.71326113e+00"/>
    <Spectator SpecIndex="13" Expression="dibos_eta" Label="dibos_eta" Title="F" Unit="" Internal="dibos_eta" Type="F" Min="-6.48222923e+00" Max="6.77470207e+00"/>
    <Spectator SpecIndex="14" Expression="dibos_mt" Label="dibos_mt" Title="F" Unit="" Internal="dibos_mt" Type="F" Min="2.78435608e+02" Max="5.91808154e+03"/>
    <Spectator SpecIndex="15" Expression="dibos_phi" Label="dibos_phi" Title="F" Unit="" Internal="dibos_phi" Type="F" Min="-3.14156890e+00" Max="3.14154935e+00"/>
    <Spectator SpecIndex="16" Expression="dibos_pt" Label="dibos_pt" Title="F" Unit="" Internal="dibos_pt" Type="F" Min="7.17565894e-01" Max="2.80505176e+03"/>
    <Spectator SpecIndex="17" Expression="dilep_eta" Label="dilep_eta" Title="F" Unit="" Internal="dilep_eta" Type="F" Min="-4.05583239e+00" Max="3.82504773e+00"/>
    <Spectator SpecIndex="18" Expression="dilep_m" Label="dilep_m" Title="F" Unit="" Internal="dilep_m" Type="F" Min="4.25420493e-01" Max="1.85691162e+03"/>
    <Spectator SpecIndex="19" Expression="dilep_mt" Label="dilep_mt" Title="F" Unit="" Internal="dilep_mt" Type="F" Min="5.57104530e+01" Max="2.93740771e+03"/>
    <Spectator SpecIndex="20" Expression="dilep_phi" Label="dilep_phi" Title="F" Unit="" Internal="dilep_phi" Type="F" Min="-3.14158678e+00" Max="3.14157081e+00"/>
    <Spectator SpecIndex="21" Expression="dilep_pt" Label="dilep_pt" Title="F" Unit="" Internal="dilep_pt" Type="F" Min="8.52797449e-01" Max="2.91678809e+03"/>
    <Spectator SpecIndex="22" Expression="evt" Label="evt" Title="I" Unit="" Internal="evt" Type="F" Min="3.20000000e+01" Max="3.54417984e+08"/>
    <Spectator SpecIndex="23" Expression="genWeight" Label="genWeight" Title="F" Unit="" Internal="genWeight" Type="F" Min="-3.03359375e+02" Max="3.16468750e+02"/>
    <Spectator SpecIndex="24" Expression="gid" Label="gid" Title="I" Unit="" Internal="gid" Type="F" Min="1.00000000e+00" Max="1.50000000e+01"/>
    <Spectator SpecIndex="25" Expression="L1PFWeight" Label="L1PFWeight" Title="F" Unit="" Internal="L1PFWeight" Type="F" Min="3.42070013e-02" Max="1.00000000e+00"/>
    <Spectator SpecIndex="26" Expression="lep1_idEffWeight" Label="lep1_idEffWeight" Title="F" Unit="" Internal="lep1_idEffWeight" Type="F" Min="8.67357492e-01" Max="1.06021249e+00"/>
    <Spectator SpecIndex="27" Expression="lep1_iso" Label="lep1_iso" Title="F" Unit="" Internal="lep1_iso" Type="F" Min="0.00000000e+00" Max="1.49991751e-01"/>
    <Spectator SpecIndex="28" Expression="lep1_m" Label="lep1_m" Title="F" Unit="" Internal="lep1_m" Type="F" Min="5.10999991e-04" Max="1.05658375e-01"/>
    <Spectator SpecIndex="29" Expression="lep1_phi" Label="lep1_phi" Title="F" Unit="" Internal="lep1_phi" Type="F" Min="-3.14160156e+00" Max="3.14160156e+00"/>
    <Spectator SpecIndex="30" Expression="lep1_pt" Label="lep1_pt" Title="F" Unit="" Internal="lep1_pt" Type="F" Min="2.50003796e+01" Max="2.50739941e+03"/>
    <Spectator SpecIndex="31" Expression="lep1_q" Label="lep1_q" Title="F" Unit="" Internal="lep1_q" Type="F" Min="-1.00000000e+00" Max="1.00000000e+00"/>
    <Spectator SpecIndex="32" Expression="lep1_trigEffWeight" Label="lep1_trigEffWeight" Title="F" Unit="" Internal="lep1_trigEffWeight" Type="F" Min="1.00000000e+00" Max="1.00000000e+00"/>
    <Spectator SpecIndex="33" Expression="lep2_eta" Label="lep2_eta" Title="F" Unit="" Internal="lep2_eta" Type="F" Min="-9.99000000e+02" Max="-9.99000000e+02"/>
    <Spectator SpecIndex="34" Expression="lep2_idEffWeight" Label="lep2_idEffWeight" Title="F" Unit="" Internal="lep2_idEffWeight" Type="F" Min="1.00000000e+00" Max="1.00000000e+00"/>
    <Spectator SpecIndex="35" Expression="lep2_phi" Label="lep2_phi" Title="F" Unit="" Internal="lep2_phi" Type="F" Min="-9.99000000e+02" Max="-9.99000000e+02"/>
    <Spectator SpecIndex="36" Expression="lep2_pt" Label="lep2_pt" Title="F" Unit="" Internal="lep2_pt" Type="F" Min="-9.99000000e+02" Max="-9.99000000e+02"/>
    <Spectator SpecIndex="37" Expression="lep2_trigEffWeight" Label="lep2_trigEffWeight" Title="F" Unit="" Internal="lep2_trigEffWeight" Type="F" Min="1.00000000e+00" Max="1.00000000e+00"/>
    <Spectator SpecIndex="38" Expression="lumin" Label="lumin" Title="F" Unit="" Internal="lumin" Type="F" Min="3.58670586e+04" Max="5.97400000e+04"/>
    <Spectator SpecIndex="39" Expression="mcWeight" Label="mcWeight" Title="F" Unit="" Internal="mcWeight" Type="F" Min="3.87841065e-10" Max="4.60524570e-05"/>
    <Spectator SpecIndex="40" Expression="MET" Label="MET" Title="F" Unit="" Internal="MET" Type="F" Min="3.00006599e+01" Max="2.71393384e+03"/>
    <Spectator SpecIndex="41" Expression="MET_phi" Label="MET_phi" Title="F" Unit="" Internal="MET_phi" Type="F" Min="-3.14159036e+00" Max="3.14156795e+00"/>
    <Spectator SpecIndex="42" Expression="nBtag_loose" Label="nBtag_loose" Title="I" Unit="" Internal="nBtag_loose" Type="F" Min="0.00000000e+00" Max="0.00000000e+00"/>
    <Spectator SpecIndex="43" Expression="nBtag_medium" Label="nBtag_medium" Title="I" Unit="" Internal="nBtag_medium" Type="F" Min="0.00000000e+00" Max="0.00000000e+00"/>
    <Spectator SpecIndex="44" Expression="neu_pz_type0" Label="neu_pz_type0" Title="F" Unit="" Internal="neu_pz_type0" Type="F" Min="-9.99000000e+02" Max="-9.99000000e+02"/>
    <Spectator SpecIndex="45" Expression="nJet30" Label="nJet30" Title="I" Unit="" Internal="nJet30" Type="F" Min="2.00000000e+00" Max="1.30000000e+01"/>
    <Spectator SpecIndex="46" Expression="nJet50" Label="nJet50" Title="I" Unit="" Internal="nJet50" Type="F" Min="2.00000000e+00" Max="1.10000000e+01"/>
    <Spectator SpecIndex="47" Expression="nPV" Label="nPV" Title="F" Unit="" Internal="nPV" Type="F" Min="1.00000000e+00" Max="9.10000000e+01"/>
    <Spectator SpecIndex="48" Expression="puWeight" Label="puWeight" Title="F" Unit="" Internal="puWeight" Type="F" Min="0.00000000e+00" Max="4.69509277e+01"/>
    <Spectator SpecIndex="49" Expression="run" Label="run" Title="I" Unit="" Internal="run" Type="F" Min="1.00000000e+00" Max="1.00000000e+00"/>
    <Spectator SpecIndex="50" Expression="vbf1_AK4_m" Label="vbf1_AK4_m" Title="F" Unit="" Internal="vbf1_AK4_m" Type="F" Min="2.63671875e+00" Max="3.87000000e+02"/>
    <Spectator SpecIndex="51" Expression="vbf1_AK4_phi" Label="vbf1_AK4_phi" Title="F" Unit="" Internal="vbf1_AK4_phi" Type="F" Min="-3.14160156e+00" Max="3.14160156e+00"/>
    <Spectator SpecIndex="52" Expression="vbf1_AK4_pt" Label="vbf1_AK4_pt" Title="F" Unit="" Internal="vbf1_AK4_pt" Type="F" Min="5.00070686e+01" Max="2.70188965e+03"/>
    <Spectator SpecIndex="53" Expression="vbf2_AK4_m" Label="vbf2_AK4_m" Title="F" Unit="" Internal="vbf2_AK4_m" Type="F" Min="1.43847656e+00" Max="2.33500000e+02"/>
    <Spectator SpecIndex="54" Expression="vbf2_AK4_phi" Label="vbf2_AK4_phi" Title="F" Unit="" Internal="vbf2_AK4_phi" Type="F" Min="-3.14160156e+00" Max="3.14160156e+00"/>
    <Spectator SpecIndex="55" Expression="vbf2_AK4_pt" Label="vbf2_AK4_pt" Title="F" Unit="" Internal="vbf2_AK4_pt" Type="F" Min="5.00001640e+01" Max="1.59155005e+03"/>
    <Spectator SpecIndex="56" Expression="vbf_phi" Label="vbf_phi" Title="F" Unit="" Internal="vbf_phi" Type="F" Min="-3.14157367e+00" Max="3.14157915e+00"/>
    <Spectator SpecIndex="57" Expression="vbf_pt" Label="vbf_pt" Title="F" Unit="" Internal="vbf_pt" Type="F" Min="4.37140286e-01" Max="2.74169897e+03"/>
    <Spectator SpecIndex="58" Expression="year" Label="year" Title="I" Unit="" Internal="year" Type="F" Min="2.01600000e+03" Max="2.01800000e+03"/>
    <Spectator SpecIndex="59" Expression="class_id" Label="class_id" Title="I" Unit="" Internal="class_id" Type="F" Min="0.00000000e+00" Max="1.00000000e+00"/>
  </Spectators>
  <Classes NClass="2">
    <Class Name="Signal" Index="0"/>
    <Class Name="Background" Index="1"/>
  </Classes>
  <Transformations NTransformations="1">
    <Transform Name="Normalize">
      <Selection>
        <Input NInputs="15">
          <Input Type="Variable" Label="bos_PuppiAK8_eta" Expression="bos_PuppiAK8_eta"/>
          <Input Type="Variable" Label="bos_PuppiAK8_m_sd0_corr" Expression="bos_PuppiAK8_m_sd0_corr"/>
          <Input Type="Variable" Label="bos_PuppiAK8_tau2tau1" Expression="bos_PuppiAK8_tau2tau1"/>
          <Input Type="Variable" Label="dibos_m" Expression="dibos_m"/>
          <Input Type="Variable" Label="lep1_eta" Expression="lep1_eta"/>
          <Input Type="Variable" Label="nJet30f" Expression="nJet30f"/>
          <Input Type="Variable" Label="vbf1_AK4_eta" Expression="vbf1_AK4_eta"/>
          <Input Type="Variable" Label="vbf1_AK4_qgid" Expression="vbf1_AK4_qgid"/>
          <Input Type="Variable" Label="vbf2_AK4_eta" Expression="vbf2_AK4_eta"/>
          <Input Type="Variable" Label="vbf2_AK4_qgid" Expression="vbf2_AK4_qgid"/>
          <Input Type="Variable" Label="vbf_deta" Expression="vbf_deta"/>
          <Input Type="Variable" Label="vbf_eta" Expression="vbf_eta"/>
          <Input Type="Variable" Label="vbf_m" Expression="vbf_m"/>
          <Input Type="Variable" Label="zeppHad" Expression="zeppHad"/>
          <Input Type="Variable" Label="zeppLep" Expression="zeppLep"/>
        </Input>
        <Output NOutputs="15">
          <Output Type="Variable" Label="bos_PuppiAK8_eta" Expression="bos_PuppiAK8_eta"/>
          <Output Type="Variable" Label="bos_PuppiAK8_m_sd0_corr" Expression="bos_PuppiAK8_m_sd0_corr"/>
          <Output Type="Variable" Label="bos_PuppiAK8_tau2tau1" Expression="bos_PuppiAK8_tau2tau1"/>
          <Output Type="Variable" Label="dibos_m" Expression="dibos_m"/>
          <Output Type="Variable" Label="lep1_eta" Expression="lep1_eta"/>
          <Output Type="Variable" Label="nJet30f" Expression="nJet30f"/>
          <Output Type="Variable" Label="vbf1_AK4_eta" Expression="vbf1_AK4_eta"/>
          <Output Type="Variable" Label="vbf1_AK4_qgid" Expression="vbf1_AK4_qgid"/>
          <Output Type="Variable" Label="vbf2_AK4_eta" Expression="vbf2_AK4_eta"/>
          <Output Type="Variable" Label="vbf2_AK4_qgid" Expression="vbf2_AK4_qgid"/>
          <Output Type="Variable" Label="vbf_deta" Expression="vbf_deta"/>
          <Output Type="Variable" Label="vbf_eta" Expression="vbf_eta"/>
          <Output Type="Variable" Label="vbf_m" Expression="vbf_m"/>
          <Output Type="Variable" Label="zeppHad" Expression="zeppHad"/>
          <Output Type="Variable" Label="zeppLep" Expression="zeppLep"/>
        </Output>
      </Selection>
      <Class ClassIndex="0">
        <Ranges>
          <Range Index="0" Min="-2.3994140625000000e+00" Max="2.3994140625000000e+00"/>
          <Range Index="1" Min="6.5062500000000000e+01" Max="1.0493750000000000e+02"/>
          <Range Index="2" Min="5.0444163382053375e-02" Max="5.4980343580245972e-01"/>
          <Range Index="3" Min="1.3990316772460938e+02" Max="3.6373686523437500e+03"/>
          <Range Index="4" Min="-2.4956054687500000e+00" Max="2.4931640625000000e+00"/>
          <Range Index="5" Min="2.0000000000000000e+00" Max="9.0000000000000000e+00"/>
          <Range Index="6" Min="-4.6376953125000000e+00" Max="4.6230468750000000e+00"/>
          <Range Index="7" Min="6.4039230346679688e-04" Max="1.0000000000000000e+00"/>
          <Range Index="8" Min="-4.6708984375000000e+00" Max="4.6611328125000000e+00"/>
          <Range Index="9" Min="2.5439262390136719e-04" Max="1.0000000000000000e+00"/>
          <Range Index="10" Min="2.5019531250000000e+00" Max="8.7978515625000000e+00"/>
          <Range Index="11" Min="-6.8550605773925781e+00" Max="7.0212740898132324e+00"/>
          <Range Index="12" Min="5.0016265869140625e+02" Max="8.4824726562500000e+03"/>
          <Range Index="13" Min="-3.1118164062500000e+00" Max="3.1474609375000000e+00"/>
          <Range Index="14" Min="-3.3638808727264404e+00" Max="3.2405185699462891e+00"/>
        </Ranges>
      </Class>
      <Class ClassIndex="1">
        <Ranges>
          <Range Index="0" Min="-2.3999023437500000e+00" Max="2.3999023437500000e+00"/>
          <Range Index="1" Min="6.5062500000000000e+01" Max="1.0493750000000000e+02"/>
          <Range Index="2" Min="1.4044944196939468e-02" Max="5.4997301101684570e-01"/>
          <Range Index="3" Min="1.2892057800292969e+02" Max="5.9150512695312500e+03"/>
          <Range Index="4" Min="-2.5000000000000000e+00" Max="2.4990234375000000e+00"/>
          <Range Index="5" Min="2.0000000000000000e+00" Max="1.3000000000000000e+01"/>
          <Range Index="6" Min="-4.6679687500000000e+00" Max="4.6582031250000000e+00"/>
          <Range Index="7" Min="3.3294782042503357e-08" Max="1.0000000000000000e+00"/>
          <Range Index="8" Min="-4.6845703125000000e+00" Max="4.6904296875000000e+00"/>
          <Range Index="9" Min="1.2116506695747375e-06" Max="1.0000000000000000e+00"/>
          <Range Index="10" Min="2.5001220703125000e+00" Max="8.8505859375000000e+00"/>
          <Range Index="11" Min="-8.2946529388427734e+00" Max="7.3777565956115723e+00"/>
          <Range Index="12" Min="5.0000027465820312e+02" Max="7.7199687500000000e+03"/>
          <Range Index="13" Min="-3.2145996093750000e+00" Max="3.2746582031250000e+00"/>
          <Range Index="14" Min="-3.4847786426544189e+00" Max="3.3985621929168701e+00"/>
        </Ranges>
      </Class>
      <Class ClassIndex="2">
        <Ranges>
          <Range Index="0" Min="-2.3999023437500000e+00" Max="2.3999023437500000e+00"/>
          <Range Index="1" Min="6.5062500000000000e+01" Max="1.0493750000000000e+02"/>
          <Range Index="2" Min="1.4044944196939468e-02" Max="5.4997301101684570e-01"/>
          <Range Index="3" Min="1.2892057800292969e+02" Max="5.9150512695312500e+03"/>
          <Range Index="4" Min="-2.5000000000000000e+00" Max="2.4990234375000000e+00"/>
          <Range Index="5" Min="2.0000000000000000e+00" Max="1.3000000000000000e+01"/>
          <Range Index="6" Min="-4.6679687500000000e+00" Max="4.6582031250000000e+00"/>
          <Range Index="7" Min="3.3294782042503357e-08" Max="1.0000000000000000e+00"/>
          <Range Index="8" Min="-4.6845703125000000e+00" Max="4.6904296875000000e+00"/>
          <Range Index="9" Min="1.2116506695747375e-06" Max="1.0000000000000000e+00"/>
          <Range Index="10" Min="2.5001220703125000e+00" Max="8.8505859375000000e+00"/>
          <Range Index="11" Min="-8.2946529388427734e+00" Max="7.3777565956115723e+00"/>
          <Range Index="12" Min="5.0000027465820312e+02" Max="8.4824726562500000e+03"/>
          <Range Index="13" Min="-3.2145996093750000e+00" Max="3.2746582031250000e+00"/>
          <Range Index="14" Min="-3.4847786426544189e+00" Max="3.3985621929168701e+00"/>
        </Ranges>
      </Class>
    </Transform>
  </Transformations>
  <MVAPdfs/>
  <Weights NetDepth="2" InputDepth="1" InputHeight="1" InputWidth="15" BatchSize="1" BatchDepth="1" BatchHeight="30" BatchWidth="15" LossFunction="C" Initialization="F" Regularization="0" OutputFunction="S" WeightDecay="0.0000000000000000e+00">
    <DenseLayer Width="256" ActivationFunction="1">
      <Weights Rows="256" Columns="15">
        -1.932243e-02  8.766682e-02  1.055533e-01  8.252326e-02  4.281075e-02  -1.161166e-01  -1.489935e-01  -2.061394e-02  -7.440796e-03  -2.296068e-03  -8.735764e-02  8.836750e-02  -1.136211e-01  -1.136483e-01  7.141996e-02  1.028892e-01  -4.231235e-03  -3.274912e-02  -3.594620e-01  -1.020494e-01  7.854860e-02  -4.637663e-02  -1.237820e-02  2.848800e-02  -3.749277e-02  1.310351e-01  5.157136e-02  -1.490117e-01  -7.002438e-02  -1.076233e-01  -2.877288e-02  -1.229882e-01  1.052357e-01  1.813143e-02  -2.135077e-01  7.427957e-03  -5.490951e-02  -7.609478e-03  3.837243e-02  8.471721e-02  8.414742e-02  -9.193780e-02  3.404363e-02  4.783244e-02  -9.508339e-02  -3.630516e-02  -1.641760e-01  -9.499098e-03  -6.158410e-02  2.838261e-01  2.793455e-05  5.272370e-03  -9.997787e-02  -9.068191e-02  3.083743e-02  -8.726578e-02  -1.810869e-02  -2.404368e-01  1.037519e-01  -1.375788e-01  9.215515e-02  -1.040598e-01  -2.549569e-02  -7.550994e-02  1.483136e-02  1.419218e-01  1.121992e-01  -1.619804e-02  -5.293706e-03  -2.966928e-02  1.183062e-01  4.696760e-02  3.647956e-02  -1.488933e-02  -4.605368e-02  -7.389944e-02  7.661965e-02  5.929297e-02  -7.408038e-02  -9.571316e-02  -7.282835e-02  9.886507e-02  1.747636e-01  1.392081e-01  -5.116840e-02  -1.015282e-01  -8.731986e-02  8.821005e-02  -1.175522e-01  3.284403e-03  1.105789e-01  -1.617396e-01  -8.308247e-02  -6.288136e-02  1.361311e-01  6.293772e-03  -6.135209e-02  -1.595928e-01  9.436129e-02  -9.202143e-02  1.790052e-01  -1.137599e-01  -1.710133e-01  -2.631813e-02  -9.020807e-02  9.546146e-02  -6.353986e-02  -2.573335e-02  -6.067760e-02  1.367569e-01  -4.855110e-02  7.153541e-03  1.083644e-01  1.152996e-01  8.992615e-02  1.293060e-01  -1.709737e-01  2.497835e-02  -1.180336e-01  -5.942671e-02  -1.118772e-01  -2.693438e-02  1.663609e-01  -1.693821e-01  1.118598e-01  -6.937405e-02  1.196226e-01  3.917590e-03  8.409368e-02  -5.625970e-03  9.304152e-02  -3.612226e-02  5.919597e-02  -2.161369e-01  -1.006557e-01  -2.393769e-01  -2.041169e-02  -1.638006e-01  2.044567e-02  6.674987e-02  1.680433e-02  -3.138638e-02  4.717142e-02  -7.871811e-02  -2.163638e-02  -7.252051e-02  -1.151591e-01  -9.263656e-03  -2.227093e-01  -8.100102e-02  -2.078445e-01  3.861279e-02  5.592355e-02  1.295618e-01  3.962540e-01  -2.549553e-01  -2.251733e-01  -1.571855e-01  -1.696712e-02  -9.619850e-02  -2.980587e-01  -1.702272e-01  -4.005224e-02  7.764755e-02  9.518793e-02  -2.256461e-01  -2.017966e-02  4.487371e-03  1.727602e-01  2.518722e-02  -2.647545e-01  -9.596252e-02  7.377902e-02  -1.235335e-01  2.202148e-01  -2.221084e-02  8.307855e-02  1.977736e-02  -1.054465e-01  1.599616e-01  -1.248193e-02  6.479865e-02  -2.127495e-02  -6.836031e-02  -1.655419e-01  3.927996e-02  6.501997e-02  -1.516710e-01  -2.250862e-01  1.388790e-01  -1.398838e-01  -3.531128e-02  8.272256e-02  -9.399859e-02  -1.490050e-01  -1.269673e-01  -1.263391e-01  2.757466e-03  1.552120e-01  -9.742925e-02  -3.640386e-02  -1.985828e-02  1.003812e-01  1.599015e-01  -1.311267e-01  -1.285140e-01  -1.596119e-01  2.126095e-02  5.323095e-02  -5.223681e-02  -2.579512e-03  3.117127e-02  -1.987528e-01  8.370697e-02  -8.463883e-02  -1.691618e-01  -2.067229e-01  -4.637174e-02  -7.460358e-02  -2.577471e-01  3.631403e-02  -3.224289e-01  -3.500822e-03  9.084374e-02  -9.937081e-03  -1.410356e-01  -5.448051e-02  -1.299620e-01  -3.460391e-02  1.481435e-02  -8.332910e-02  1.008342e-01  7.220172e-02  -1.037387e-01  8.989821e-02  -5.750355e-02  -1.117814e-01  3.021785e-02  -1.331078e-01  4.358644e-02  2.085830e-02  -2.995166e-02  9.622180e-02  -1.894123e-01  -3.332251e-01  8.874378e-02  -7.781500e-02  -1.049993e-02  5.891010e-02  2.790062e-02  8.787323e-02  1.107334e-01  1.604492e-01  -1.950470e-01  -5.356893e-02  -6.748626e-02  -4.617737e-01  4.056011e-02  1.363584e-01  -7.050029e-02  -3.700141e-02  1.421659e-01  8.831213e-02  -1.279411e-02  4.203483e-02  -1.989305e-01  -4.914011e-02  -6.667864e-02  -1.079069e-01  -6.545177e-02  -1.537284e-01  -2.845748e-03  -7.232805e-02  3.537551e-02  -3.613793e-02  7.862993e-02  1.128222e-01  6.852733e-02  -5.776345e-02  1.392040e-01  1.135878e-02  4.193075e-02  1.326461e-01  -3.852441e-02  -1.034800e-01  6.101811e-03  9.654242e-03  -3.174448e-01  2.223530e-01  -1.022648e-02  -3.244139e-01  1.226603e-01  3.242378e-02  -3.104999e-02  7.175755e-03  2.059080e-01  -8.930757e-03  -5.454476e-05  -1.166761e-01  1.262658e-01  8.321273e-02  -5.713066e-02  4.225655e-02  -9.837659e-02  2.712424e-02  1.022809e-02  1.231323e-01  4.540665e-02  4.553830e-02  1.518917e-01  -7.891477e-02  -6.223327e-02  -2.066202e-02  -1.225654e-01  4.080157e-02  8.542506e-02  7.478426e-02  9.249553e-02  -1.103571e-01  4.686489e-02  3.205442e-02  -7.922626e-02  -1.053921e-01  1.336673e-01  -7.359345e-02  1.260156e-01  -1.068945e-02  3.991857e-02  -1.260221e-01  -1.009251e-01  -1.409383e-02  -1.326870e-02  9.297405e-03  3.795492e-02  -1.087389e-02  2.312446e-02  -5.102981e-02  -2.143199e-02  -3.312185e-02  7.201218e-05  9.936922e-02  9.930735e-02  -4.672194e-01  8.058336e-02  2.604417e-02  1.868491e-01  -1.350133e-01  1.510557e-01  -2.788121e-02  -6.719162e-02  3.587496e-02  -8.845270e-03  -7.462373e-02  -1.627952e-01  8.070925e-02  1.747630e-01  6.808221e-02  -2.578622e-01  2.055250e-01  8.115852e-02  1.358255e-01  9.283852e-02  -8.234853e-02  7.949508e-02  -2.361996e-02  1.588623e-01  4.785513e-02  -1.966926e-01  -1.311312e-01  1.341138e-01  -8.260196e-02  -1.465693e-01  1.714968e-02  -1.140954e-01  3.477799e-02  7.817724e-02  -6.835479e-03  -1.087490e-01  -2.539290e-01  -1.339089e-01  8.236625e-02  1.511218e-01  -2.404106e-02  1.870145e-01  1.924381e-02  2.483538e-01  -7.135115e-02  -1.211561e-01  -1.712014e-01  -1.156982e-01  9.865046e-03  -1.783249e-01  6.675310e-02  1.098966e-01  6.825197e-02  4.823481e-02  -7.234661e-02  -1.222257e-01  1.686566e-01  1.038672e-01  -9.787130e-02  -2.070008e-02  -1.392947e-01  -1.375552e-01  -4.842899e-02  1.236455e-01  -2.299312e-01  1.128171e-01  1.377353e-01  -2.541308e-01  -9.387267e-02  3.464511e-02  -3.948458e-03  2.171239e-02  -1.341765e-02  -1.946169e-01  4.682424e-02  -1.175322e-01  -7.621430e-02  1.497135e-01  1.469896e-01  -9.509137e-02  -4.017914e-02  -1.470747e-01  -9.265437e-02  9.540945e-02  -8.360302e-02  9.795491e-02  8.642150e-02  -1.681770e-01  -1.453305e-01  1.564750e-01  -1.721825e-01  4.174501e-02  2.264200e-02  9.901220e-02  4.369476e-02  2.815307e-02  5.379597e-02  -1.382739e-01  9.615932e-02  7.146117e-02  1.348753e-01  -5.398098e-02  6.112415e-02  -9.533567e-02  1.748097e-01  1.794767e-01  1.095043e-02  -2.194331e-02  -1.526850e-01  6.782483e-02  -1.398650e-01  1.323453e-01  9.794640e-02  -1.236710e-01  -1.338909e-01  -1.216918e-01  1.428950e-02  -5.167390e-02  -7.163104e-02  -1.982475e-01  6.992029e-02  1.064231e-01  -1.986748e-02  -5.955316e-02  -5.963629e-02  -1.531434e-01  -3.976266e-01  1.195630e-01  2.482068e-01  -1.297626e-01  -4.207913e-02  -1.739404e-01  -2.675052e-02  5.155947e-01  2.123659e-02  -2.942823e-01  3.270777e-02  1.068424e-01  -8.638261e-02  1.176604e-01  1.007202e-01  6.158474e-02  -1.675076e-01  -1.392316e-01  4.705760e-02  6.688264e-02  2.023661e-01  -1.072166e-01  1.704538e-01  -1.111322e-02  2.443391e-01  -7.504252e-02  -2.464408e-02  -8.783186e-03  -1.092572e-01  -1.358807e-01  -1.226052e-01  -9.871333e-02  7.322633e-02  1.071946e-01  -1.335950e-01  -1.436172e-02  5.750112e-02  2.251152e-02  1.943575e-02  9.432582e-02  1.423921e-01  -5.364024e-02  1.313535e-01  -2.244077e-02  -1.432616e-01  7.998097e-02  1.095002e-01  4.144121e-02  3.403158e-02  -1.543653e-01  1.215283e-02  7.765839e-02  -7.350466e-02  -6.200302e-02  2.192583e-02  5.685178e-03  -7.109449e-02  1.816681e-02  4.855969e-02  1.202042e-01  -3.078818e-01  -6.186344e-02  -1.798160e-02  1.030456e-01  -1.607927e-01  1.807922e-02  2.549053e-01  -1.907764e-01  1.527341e-02  -3.266307e-01  -1.831882e-01  1.303658e-01  -1.633110e-01  -3.299662e-01  1.259958e-01  -1.446838e-01  -3.956361e-02  -3.252298e-02  -2.026354e-01  3.145162e-02  -1.801820e-01  3.676639e-02  2.586728e-01  1.345945e-02  3.028037e-01  -6.200078e-02  5.438040e-02  6.599221e-02  3.201699e-02  6.985867e-02  7.984600e-03  6.681208e-02  4.625849e-02  -1.353440e-01  -1.470274e-01  -8.622282e-02  -8.216498e-02  7.409520e-02  7.035098e-02  -1.540612e-01  -1.078302e-01  4.061129e-02  5.978695e-02  -3.361961e-02  -1.334734e-01  1.612474e-01  9.540560e-02  -1.229461e-01  8.046973e-02  1.431383e-01  1.483688e-01  5.889506e-02  7.641510e-02  -3.305536e-03  4.539980e-02  -1.366910e-01  9.906408e-02  -2.734100e-03  8.278681e-02  1.670407e-01  -5.797873e-02  3.492131e-02  7.545476e-02  -4.172372e-02  1.104143e-01  -6.150236e-02  1.073771e-01  -6.816605e-02  -1.180581e-02  -2.760791e-01  -5.912721e-02  -1.327275e-01  2.548409e-02  -1.204226e-01  -3.083380e-02  -2.237926e-01  -1.548391e-01  -3.472503e-02  5.022426e-02  2.516519e-02  1.135892e-01  -9.700598e-02  6.040346e-02  1.049759e-01  -1.566931e-01  6.557261e-02  -6.168889e-02  -7.467142e-02  3.016876e-01  1.094775e-01  -1.914553e-01  -2.497994e-01  6.615406e-02  -4.770894e-02  -1.479177e-01  -1.807580e-02  -3.513130e-02  4.101769e-02  5.616137e-02  1.987520e-01  -1.702260e-01  -3.891040e-02  2.161190e-02  -1.168201e-01  -8.475285e-02  -1.443802e-01  1.583085e-02  8.999815e-02  -1.681355e-01  8.710603e-02  -1.626427e-01  6.139522e-02  2.340709e-01  3.993674e-02  8.310246e-02  3.467390e-02  1.168774e-01  2.457633e-02  -4.269294e-02  1.376934e-01  2.232346e-02  -6.915571e-02  9.198634e-02  3.729356e-02  1.298828e-01  7.776809e-02  -3.452842e-02  1.139242e-01  -8.138984e-02  7.961845e-02  -6.896608e-02  -1.236685e-01  -2.741734e-03  -1.728780e-01  1.375514e-01  -6.361240e-02  4.110116e-02  -1.062229e-01  1.517393e-01  1.780444e-02  1.388249e-02  -1.491852e-01  -1.576318e-01  -4.000562e-02  8.382463e-02  -1.149191e-01  5.520766e-02  -1.444625e-01  -1.385490e-01  -1.838074e-02  -1.219515e-01  -5.291318e-02  1.410138e-01  2.545681e-02  -1.310952e-01  6.600754e-02  1.222923e-01  -1.380536e-01  -8.833150e-02  1.493881e-01  -6.221109e-02  3.382757e-02  5.930259e-02  -6.064023e-02  4.868754e-02  8.626328e-02  7.566552e-03  7.966445e-02  1.022587e-01  3.263708e-02  -1.543918e-01  -1.447351e-01  1.002019e-01  3.916684e-02  2.775456e-02  1.101503e-01  -5.928171e-02  1.177350e-01  3.443628e-02  8.808368e-02  1.045150e-01  -1.102583e-02  5.692365e-02  -3.970752e-02  -1.077185e-01  1.114676e-01  -1.333462e-01  3.606373e-02  1.103728e-01  -5.123090e-02  -1.157305e-01  -1.387991e-01  -1.156613e-01  8.212467e-02  6.691360e-02  -4.548550e-02  5.361573e-02  -1.200037e-02  -1.036993e-01  -1.408929e-01  1.443267e-01  -9.661452e-02  3.959185e-03  -6.024239e-02  -1.371701e-01  -1.519803e-01  -1.061631e-01  3.325767e-02  -1.170330e-02  2.301659e-02  -3.772322e-02  6.283031e-02  -7.645433e-02  -9.007876e-02  -1.525833e-01  1.197521e-01  2.861538e-03  -1.040270e-01  1.712188e-01  -4.898125e-02  -1.299853e-01  3.242287e-02  1.358225e-01  1.642897e-01  1.329373e-01  -1.437103e-01  3.572021e-02  -7.637159e-02  -8.143374e-03  1.659470e-01  2.577498e-03  -7.975520e-02  -1.402158e-01  1.740514e-01  -1.999472e-01  1.941557e-01  1.175943e-01  7.578698e-02  -1.774460e-01  -2.759989e-02  1.262102e-01  1.818836e-01  -1.412172e-02  -4.628546e-02  -1.451250e-01  1.549793e-01  -5.445266e-02  -1.959637e-01  5.589043e-02  1.103944e-01  -9.156235e-02  6.305493e-02  -1.592671e-01  -8.623221e-02  -4.695509e-02  -2.414448e-01  7.067905e-02  -2.278472e-02  9.228859e-02  -1.048841e-01  1.188061e-01  -5.227425e-02  1.580857e-01  1.184713e-01  -1.070610e-01  -1.282080e-01  -7.752839e-02  1.098085e-01  4.320469e-02  -8.395118e-02  5.692228e-02  1.429413e-01  8.234411e-02  -1.643900e-01  4.003853e-03  1.250462e-01  -1.620851e-01  1.020415e-01  2.192445e-01  -4.618039e-02  -1.375126e-01  5.084884e-03  -5.120806e-02  3.096111e-02  1.258626e-01  -1.057090e-01  5.945643e-02  -3.596239e-02  -6.931292e-02  -1.227280e-01  -2.897434e-02  1.032000e-01  4.892722e-02  8.871748e-03  5.740433e-02  -7.493053e-02  -7.298477e-03  -9.186617e-02  -1.218676e-01  -6.524672e-02  8.517754e-02  1.974624e-01  -5.940522e-04  -2.313360e-02  -9.860441e-02  -9.151135e-02  1.509879e-01  1.702486e-01  -1.161527e-01  -4.082030e-02  -3.273678e-02  -6.903864e-02  -1.320774e-01  -7.113227e-02  5.887533e-02  8.828941e-02  8.010053e-02  -2.090290e-01  -1.211063e-01  1.019762e-01  4.490669e-02  -3.232463e-02  -1.709556e-01  3.837129e-02  2.092021e-02  9.979613e-02  6.786221e-02  8.399034e-03  -1.776708e-01  9.032017e-02  -2.014302e-01  6.825075e-02  3.349755e-02  -7.836677e-02  1.557108e-01  2.200197e-01  6.088835e-02  -1.337314e-01  -1.176150e-01  -9.266141e-02  -1.537131e-01  4.744576e-02  -2.341447e-02  -7.447512e-02  3.140473e-02  -7.823533e-02  -1.228607e-01  -5.034328e-02  -2.672755e-02  -2.000331e-02  -1.659220e-01  -1.306198e-01  -8.202294e-02  -8.154605e-02  1.107001e-02  1.148882e-01  1.570001e-01  3.700036e-02  5.731674e-02  -8.873067e-02  -1.159807e-01  1.233126e-01  3.256192e-02  3.135631e-02  1.250301e-03  -1.342565e-02  -7.127607e-02  -1.140589e-01  1.963045e-02  -3.392498e-01  1.627894e-02  -5.437009e-02  -3.228781e-02  -4.663957e-02  -8.834819e-02  2.166020e-01  9.222216e-02  -9.701150e-02  1.695890e-02  4.121384e-02  -3.072908e-03  3.403591e-02  -2.087845e-01  2.569309e-02  -4.909458e-01  2.217432e-02  1.978862e-02  -5.674666e-02  8.278763e-02  6.339953e-02  -7.570417e-02  5.659955e-02  -2.818767e-02  -5.556993e-02  -7.601102e-02  1.971862e-02  -1.187651e-01  -4.652785e-02  1.034978e-01  5.374632e-02  1.667720e-02  2.826448e-02  -1.312896e-01  1.093730e-01  1.058101e-01  9.456747e-03  -1.448802e-01  -5.306995e-02  -9.997610e-04  -8.238024e-02  9.483431e-02  3.190923e-02  5.387063e-02  -1.535821e-01  -1.960767e-02  1.522358e-01  6.549026e-02  1.287124e-01  6.917512e-02  1.338434e-01  1.036442e-01  -4.141924e-02  1.254264e-01  -2.567710e-02  -1.068414e-02  8.001070e-02  -6.766047e-02  7.297089e-02  -3.057844e-02  7.609118e-02  7.641960e-02  1.449702e-01  -4.782791e-02  -5.326039e-02  -1.791062e-01  -6.597362e-02  1.254332e-01  1.613074e-01  1.231500e-01  -9.406003e-03  8.369542e-02  1.439134e-02  3.524216e-02  1.444600e-01  -6.230594e-02  2.914142e-02  2.223796e-01  5.822982e-02  3.532450e-02  8.008597e-02  2.780067e-02  -5.858636e-01  1.100375e-01  1.806373e-01  9.902547e-02  2.921979e-02  1.973396e-02  -1.214540e-01  1.497742e-01  -6.629962e-02  -2.668743e-01  1.040228e-01  -1.380052e-01  3.292074e-02  1.339989e-01  1.113750e-01  -2.398565e-03  -1.594485e-01  -1.345128e-01  -1.253994e-01  5.124116e-02  8.550405e-02  1.006408e-01  -3.135165e-02  2.378444e-02  4.865277e-02  -1.166639e-01  -5.185594e-02  -1.002844e-01  8.728315e-02  -1.228108e-01  6.187575e-02  -1.317951e-01  -1.182520e-01  9.489270e-02  -8.352839e-02  -1.441900e-02  -6.846144e-02  4.125686e-02  1.276117e-02  1.103048e-01  1.076641e-01  9.822732e-02  -1.591720e-01  -1.339904e-01  1.218376e-01  1.223057e-01  9.136206e-02  5.026475e-02  5.890283e-02  -7.636314e-02  -3.611599e-02  -4.153300e-02  5.888748e-02  -1.657233e-01  1.084164e-01  7.360173e-02  -1.553209e-01  1.703814e-01  6.664582e-02  5.109111e-03  1.425956e-01  -8.708294e-02  7.833460e-03  -9.843857e-02  -6.452154e-02  1.501242e-01  1.747715e-02  -1.127624e-01  -2.162930e-01  -8.373523e-02  6.008636e-02  4.855572e-02  -1.229907e-02  -1.339974e-01  1.230769e-01  2.274834e-02  2.702469e-02  -6.940354e-02  1.256562e-01  -4.867851e-03  1.634381e-01  4.761784e-02  1.346471e-01  2.837439e-02  7.868741e-02  -1.202023e-02  -1.623385e-01  -7.825974e-03  1.199899e-01  -1.147910e-01  3.501237e-03  -1.001209e-01  -5.859791e-03  6.323123e-02  1.595005e-01  7.743071e-03  -1.099591e-02  -1.501523e-02  -2.932868e-02  -3.944040e-02  -8.279998e-02  -1.272670e-01  1.252323e-01  -5.869441e-02  -1.000050e-01  6.980073e-02  -4.960259e-02  -1.099307e-02  -8.114917e-02  1.184999e-01  1.111098e-01  -1.143783e-01  4.975305e-02  6.822407e-02  -5.367151e-02  9.870147e-02  1.129269e-01  -7.491022e-02  1.533504e-01  -1.043659e-01  2.275010e-02  1.061719e-01  -5.398793e-02  -4.158505e-02  -4.045925e-02  -1.416761e-01  8.530313e-02  5.587636e-02  1.183371e-01  7.492086e-02  8.914872e-02  3.331530e-02  8.349901e-02  -1.092552e-01  -8.012018e-02  -1.202027e-01  -1.328430e-01  1.403210e-01  -2.737178e-02  1.179231e-01  -8.806812e-02  -2.271121e-04  -1.120061e-01  -6.355456e-02  9.920084e-02  -1.168240e-01  -1.880743e-01  -5.784871e-02  -1.790173e-01  -1.559782e-02  6.104293e-02  -6.342457e-02  1.856020e-01  1.738807e-01  -7.038618e-02  3.509975e-04  -9.503692e-02  6.722227e-02  4.505187e-02  -8.325108e-03  -1.164727e-02  1.402450e-01  1.253218e-01  -2.782559e-01  9.340105e-02  -4.586021e-02  -2.394683e-01  -1.444302e-01  5.581421e-02  5.425260e-02  -8.479301e-02  -4.238169e-02  -1.925831e-01  5.854923e-02  1.966555e-02  1.448131e-01  -2.578588e-01  -4.715564e-02  -1.696933e-01  1.234605e-01  -5.863442e-02  -2.503874e-01  -1.702121e-01  -5.359669e-02  -3.393953e-02  1.790625e-01  -3.655756e-03  1.030844e-01  4.144950e-02  -1.401159e-01  -1.033546e-01  -5.842560e-02  1.737170e-01  -8.587188e-02  -2.087718e-01  1.956953e-01  -3.715904e-02  -3.949241e-02  -1.223084e-01  3.446339e-02  1.167288e-02  -7.799380e-02  7.654492e-02  1.755832e-02  -6.333444e-02  1.622048e-01  5.660634e-02  -1.564370e-01  -1.804409e-01  2.576798e-02  -2.124128e-01  -7.033367e-02  1.977462e-02  -4.498282e-02  -5.798117e-03  5.126156e-02  -1.844655e-01  -1.035370e-01  -2.779341e-01  -1.519134e-01  2.464754e-02  -1.356340e-01  4.658079e-02  -7.389900e-02  1.039857e-01  -1.187808e-03  -1.008929e-01  4.068042e-02  1.318565e-01  4.511408e-02  -1.235788e-01  -8.936756e-02  -5.461760e-02  -1.814822e-01  9.883109e-02  -2.014038e-02  -2.028656e-01  -3.286211e-02  7.179961e-02  -4.105996e-01  8.054461e-02  1.146808e-01  7.059039e-02  -2.514551e-02  4.672290e-02  -8.913285e-03  2.508837e-01  8.252492e-02  -2.076461e-01  -1.302094e-02  -5.497949e-02  -1.087921e-01  1.968782e-01  -1.420409e-01  -2.392665e-01  -3.311594e-01  3.265284e-02  1.421648e-01  2.157257e-01  -9.737878e-02  -9.907302e-02  5.369496e-02  -9.415627e-02  -3.502086e-02  -6.467449e-02  -3.643759e-02  1.378154e-01  -6.802598e-02  -5.512200e-02  -3.201708e-02  9.042636e-02  -1.479474e-01  1.687747e-01  -1.074035e-01  2.023438e-02  -1.712956e-01  -7.002285e-02  2.947258e-02  5.409812e-02  -1.040316e-01  1.277638e-01  -6.077424e-02  7.255758e-02  -1.476071e-01  -5.646993e-02  -8.904941e-02  -8.746103e-02  -6.718411e-02  -1.066632e-01  -8.604849e-02  -1.083803e-01  9.164283e-02  -8.157097e-02  -5.462526e-02  -9.562145e-02  8.042344e-02  -4.832255e-02  1.534716e-01  -1.001454e-01  -2.130728e-01  -1.522675e-01  1.486072e-01  7.022437e-02  4.103231e-03  1.017400e-01  9.315515e-02  3.325165e-01  -1.949416e-02  -2.432172e-01  4.248881e-02  7.870439e-02  1.671626e-01  -1.718748e-02  -1.976596e-01  1.211412e-01  -1.039497e-02  -1.600503e-01  -1.549483e-01  1.246689e-01  7.644940e-02  4.691222e-02  -5.987957e-02  -1.678662e-02  -6.774954e-02  1.073889e-01  -2.634382e-03  -2.111234e-03  1.263333e-01  -5.758117e-02  -2.096018e-01  5.799670e-01  3.580344e-02  -2.384567e-01  1.077927e-01  -2.295316e-01  -6.842481e-02  -1.016764e-01  -4.166102e-03  1.667441e-01  2.086788e-01  -5.923940e-02  -8.904175e-02  1.194076e-03  1.117754e-01  -1.196692e-01  -3.945897e-02  -3.203137e-02  -6.924542e-03  2.299459e-02  5.779758e-02  -1.745289e-02  8.589537e-02  -9.039842e-02  2.612707e-02  -1.494400e-01  -5.289701e-02  -4.920218e-02  -3.841920e-03  -4.852276e-03  1.418106e-01  4.209549e-02  1.420576e-01  4.126432e-02  2.912728e-02  -3.137451e-02  6.972743e-02  -1.411037e-01  1.940110e-02  -3.419795e-02  6.555066e-02  -1.183727e-01  -1.780251e-01  9.967600e-02  -2.274491e-01  1.020371e-01  1.742266e-02  -2.592024e-01  2.487164e-02  6.706998e-02  3.435244e-02  -6.803599e-02  5.507755e-02  1.662315e-01  1.047756e-01  5.391252e-02  -1.564851e-01  1.078793e-01  1.257405e-01  6.936549e-02  8.748037e-02  4.765870e-02  -7.472529e-02  -9.806470e-02  -1.163465e-01  -1.467798e-01  -7.250753e-02  -3.160071e-01  -8.415313e-04  -3.461115e-01  -1.451529e-02  -1.199562e-01  -1.067357e-01  -6.630270e-02  -2.262162e-02  1.314510e-01  -3.375028e-03  8.493451e-02  1.010074e-01  -8.737484e-02  5.025071e-02  -2.847806e-02  1.445597e-01  9.641664e-02  1.522169e-01  1.320096e-02  -1.479435e-01  1.362799e-01  -1.289263e-01  4.625566e-02  -5.240030e-02  -1.308865e-01  8.483684e-02  1.159821e-01  3.233287e-02  -9.372836e-02  7.972135e-02  -3.192966e-02  -9.343599e-02  1.340894e-01  -1.274084e-01  -5.414489e-02  7.300211e-02  1.036762e-01  -1.395900e-02  1.404878e-02  -2.720967e-01  -1.092759e-01  1.632266e-01  -6.425121e-02  -1.833247e-03  -3.061513e-02  -4.554680e-02  1.778539e-01  5.431885e-02  -6.484630e-02  -8.600759e-02  3.205022e-02  1.223383e-01  -7.199169e-02  3.883928e-02  -3.793675e-03  1.102108e-01  1.538142e-01  1.224980e-01  7.875951e-02  4.433957e-03  1.403212e-01  1.379460e-01  1.712866e-01  1.224653e-01  5.477447e-02  -2.130010e-01  4.389274e-02  -1.186201e-02  -1.604370e-01  4.559741e-01  1.062689e-01  -1.790162e-01  7.192487e-02  -7.207790e-02  1.719551e-01  2.412573e-01  -5.252226e-02  3.264525e-01  1.509463e-01  -5.961401e-02  -6.298278e-02  1.181211e-01  -6.770942e-03  5.677472e-02  7.394508e-02  1.525554e-01  -5.767529e-02  4.722685e-02  1.732007e-02  1.255089e-01  -1.944316e-02  -5.994356e-02  1.413117e-01  1.272992e-01  6.896148e-02  2.342380e-01  -1.209124e-01  1.688776e-01  7.357208e-02  -3.893312e-01  1.839361e-02  2.111809e-01  5.734778e-02  1.119140e-01  1.090944e-01  -9.428685e-02  1.198223e-01  2.424067e-01  -1.590213e-01  -1.584211e-01  6.288373e-02  8.933850e-02  1.379171e-01  -1.544755e-02  7.618500e-02  1.785194e-01  -1.684135e-01  1.419793e-01  5.894260e-02  -3.831012e-02  -5.484472e-02  -4.595235e-02  7.123253e-02  -1.499632e-01  -6.407887e-02  -6.433415e-02  -9.603167e-02  -7.201210e-02  1.445884e-01  3.131367e-02  -1.117598e-01  2.970203e-02  -1.707627e-01  6.453034e-02  -1.491167e-01  -4.187526e-02  1.091232e-01  -5.505791e-02  8.107132e-02  7.287423e-02  -2.306749e-01  -1.785135e-01  6.836990e-02  -1.333140e-01  2.999423e-01  1.503363e-01  -1.190205e-01  4.193753e-02  -8.594042e-02  1.339976e-01  -7.235254e-02  -1.660419e-01  2.095365e-02  1.086555e-01  5.793622e-02  -2.126996e-02  6.602684e-02  -8.527963e-02  -2.731839e-02  1.268303e-01  1.336135e-01  1.391552e-01  -3.867270e-02  -6.110148e-02  -1.289479e-01  -1.157183e-01  9.560924e-02  1.429391e-01  -1.089426e-03  -6.812363e-02  2.170382e-03  7.453457e-02  -1.279469e-01  8.570985e-02  -6.383339e-02  -2.273420e-01  -1.759161e-01  1.109398e-01  8.676768e-02  -6.623455e-03  1.352390e-01  -1.164325e-02  -2.521450e-02  1.948763e-01  6.758875e-02  1.270462e-01  -7.220344e-02  -3.114664e-02  1.809045e-02  9.758222e-02  1.160948e-01  -9.254980e-02  1.872129e-01  8.077163e-02  -9.138487e-02  -7.240554e-02  1.858672e-01  1.139851e-01  -1.071154e-01  9.543023e-02  1.171613e-01  5.535159e-02  1.770978e-01  2.273937e-01  -3.848194e-01  -6.413088e-02  2.201324e-01  -4.985520e-02  3.622932e-01  2.250670e-03  -3.247516e-01  -8.311388e-02  -4.385775e-02  -2.081604e-01  -1.399654e-01  2.063586e-02  1.158823e-01  -1.168325e-01  3.383215e-02  1.717878e-02  -1.183663e-01  1.173043e-01  1.141888e-01  8.799593e-02  -1.419366e-01  1.204519e-01  -3.344443e-02  5.084310e-02  -6.810135e-02  7.471660e-02  2.087027e-01  1.898312e-01  2.623390e-01  -1.818002e-01  -1.412066e-01  -1.425306e-01  9.372752e-02  -7.568341e-02  -4.208308e-03  -7.078862e-02  2.365484e-02  1.679851e-01  -2.951627e-02  1.499628e-01  1.063098e-01  -6.348039e-02  -9.122230e-03  -1.338848e-01  8.351253e-03  -1.307272e-01  -8.596670e-02  5.038086e-02  -4.753360e-02  3.704097e-02  -8.015764e-02  1.277281e-01  -3.541320e-02  -5.607317e-02  -4.741575e-02  9.657352e-02  -4.628271e-02  -9.826462e-03  -9.473896e-03  -5.700112e-02  -8.490653e-02  3.052416e-03  7.106284e-02  -1.520511e-02  9.349824e-02  -4.076515e-03  1.569302e-01  7.443546e-02  -6.541300e-01  1.165881e-01  9.036191e-02  1.173910e-01  3.152281e-02  5.336323e-02  1.365422e-01  -4.604977e-02  -5.990877e-03  8.072314e-02  -1.488529e-03  -8.351170e-02  -6.415930e-02  4.997312e-02  -1.294214e-01  -1.699460e-02  2.254856e-02  -1.001801e-01  1.267898e-01  -9.232295e-02  2.818273e-02  -8.905042e-02  4.656236e-02  2.868492e-02  -1.800577e-01  4.684037e-02  1.503723e-01  2.218257e-02  8.689316e-02  -2.015784e-02  1.136653e-01  7.900213e-02  -8.614216e-02  3.964201e-02  -8.510151e-02  -1.018560e-01  -1.210513e-01  1.463278e-01  4.475385e-02  -4.524057e-02  1.861711e-03  -4.749094e-02  -4.738450e-02  -1.125199e-01  1.122288e-01  -1.844380e-01  -1.123591e-01  -1.259149e-01  8.354641e-02  4.919027e-02  2.848304e-02  -4.718364e-02  -1.384837e-01  1.716650e-01  1.017474e-01  2.183772e-01  -1.188347e-01  1.001628e-01  1.275443e-01  1.325115e-01  7.319027e-02  -1.087569e-01  1.165102e-01  1.153300e-01  1.698532e-02  4.942094e-03  5.116210e-03  6.258657e-02  1.393232e-01  -2.891556e-03  -5.830585e-02  6.137673e-02  3.696094e-04  1.560692e-01  2.138758e-02  -3.246592e-03  -5.353931e-02  1.222116e-02  -4.824248e-02  9.399511e-02  -2.002108e-02  1.857901e-02  -2.821718e-02  4.768581e-02  7.169224e-02  -1.336367e-01  -8.767633e-02  -1.266727e-03  1.071974e-01  2.120827e-02  1.303452e-01  -8.379015e-02  -4.446195e-02  -1.371240e-01  8.691439e-02  1.053042e-01  1.178750e-01  1.332605e-01  6.272823e-03  3.837459e-03  -9.142147e-02  -9.430244e-02  1.205415e-01  -1.483071e-01  -1.551136e-01  1.685164e-01  1.495525e-02  1.815559e-01  8.499220e-02  -4.682599e-02  -6.424346e-02  -1.241448e-01  2.585897e-01  2.953737e-02  -1.279244e-01  1.954165e-01  1.131438e-01  -7.286188e-02  -1.229233e-01  -6.094117e-02  -1.015002e-01  -2.448582e-02  -1.254781e-01  3.906713e-02  -1.579549e-01  2.541597e-02  -8.878034e-02  1.181340e-01  -9.765234e-02  -1.196972e-01  1.975209e-02  -2.021141e-01  -1.392208e-02  1.907464e-01  1.464482e-01  1.538062e-01  -1.602104e-02  7.661021e-02  1.164314e-01  5.550104e-02  -8.366504e-02  8.379679e-03  -7.801192e-02  -1.321713e-01  1.196945e-02  5.841057e-02  -1.785070e-02  -8.411916e-02  1.326234e-02  -3.228208e-02  -9.922114e-03  -1.061900e-01  3.114058e-02  -1.653328e-02  3.767338e-02  4.574297e-02  -2.737792e-01  1.222265e-01  5.596609e-02  6.567726e-02  4.691222e-02  -6.925967e-03  5.704052e-02  1.197526e-01  1.561869e-02  -3.648760e-02  1.025486e-01  1.857769e-02  2.181683e-01  -5.518752e-02  2.225650e-01  -2.594890e-01  1.325746e-02  -3.899128e-02  3.497712e-02  6.154116e-02  1.042135e-01  -4.803623e-03  2.206386e-01  -6.927803e-05  -3.054647e-01  2.632107e-01  5.044805e-02  -1.049855e-01  2.855574e-01  8.739450e-03  -2.104745e-02  -1.838253e-01  9.435721e-02  -8.927601e-02  -1.715884e-02  -4.348662e-02  2.330095e-03  -8.245560e-02  -9.437597e-02  -9.338493e-02  -5.196763e-02  1.610713e-01  -7.989488e-02  -1.067112e-02  3.729482e-03  2.557952e-02  -8.109911e-02  -2.721437e-02  6.530118e-03  6.941146e-03  9.910613e-02  -1.594310e-03  1.594777e-01  -2.684735e-02  -9.083506e-01  4.170792e-02  1.691746e-01  2.143745e-02  -7.854402e-03  1.942096e-02  -1.596282e-01  -1.593564e-01  -1.279206e-02  2.264294e-01  -7.728992e-03  1.615880e-01  1.603389e-02  2.379571e-01  -7.287814e-02  -7.527920e-01  -1.723986e-01  6.674349e-02  -8.431718e-02  7.129747e-02  -9.302881e-02  6.247993e-02  -1.063015e-01  2.795813e-02  3.491724e-02  -2.419845e-02  -7.526568e-02  -4.962359e-02  -1.354094e-01  1.094180e-01  7.351303e-02  -1.071491e-01  4.462993e-02  2.243753e-01  -3.678723e-02  -1.484965e-01  8.896147e-02  -3.217573e-02  -2.598079e-01  3.410895e-02  -8.358086e-02  -1.177772e-01  1.210053e-01  2.461289e-02  -1.764469e-01  8.273734e-04  2.055969e-01  6.392778e-02  -1.018720e-01  -1.009749e-01  4.626556e-02  5.098079e-02  7.368080e-02  1.404666e-01  1.372396e-01  1.149337e-01  7.928218e-02  -1.830081e-04  6.794644e-03  9.244472e-02  1.140925e-02  -3.678317e-02  6.710383e-03  2.734759e-01  -3.054001e-02  -2.782577e-01  5.831833e-02  4.192516e-02  -2.043761e-01  2.249446e-01  -1.367163e-01  1.234244e-01  3.143716e-02  6.114957e-02  -1.986811e-04  5.005987e-02  4.474865e-02  1.980385e-02  -4.487444e-02  4.643387e-02  7.375170e-02  4.918939e-02  -1.385310e-01  -7.601200e-03  -4.511549e-03  7.663771e-04  1.099487e-01  -7.562149e-02  -1.979967e-01  -1.408398e-01  -5.591831e-01  -7.129488e-02  1.946027e-02  -5.747979e-02  -1.948172e-02  3.528180e-02  9.967559e-02  4.396689e-03  4.537171e-02  -1.356777e-01  -1.018988e-02  -8.426484e-02  9.761520e-02  -1.070654e-01  8.369520e-03  -9.973571e-02  -3.036189e-02  1.496885e-01  -6.452874e-02  -8.639626e-03  3.016032e-02  -6.984577e-02  1.190858e-01  5.789257e-02  -1.636397e-01  -8.645553e-02  1.493030e-01  1.247108e-01  -7.880783e-02  1.187262e-01  -9.939792e-02  -2.274344e-02  -7.314207e-02  5.069742e-03  4.491854e-03  1.353393e-01  -5.856086e-02  6.815749e-02  -9.128619e-02  -7.302991e-02  -3.323437e-02  8.283602e-02  9.480292e-02  -4.024436e-02  3.579837e-03  -6.527150e-02  8.136348e-02  6.340005e-02  -2.299256e-01  5.496553e-03  4.273072e-02  -8.023433e-02  1.695869e-01  5.048450e-02  -2.456632e-02  -2.460697e-02  -6.408086e-02  7.122188e-03  -6.546396e-02  1.253114e-01  8.137453e-02  -1.482897e-01  1.677808e-01  6.095905e-02  1.101011e-01  -7.123253e-02  -5.464670e-02  5.285733e-03  1.264341e-01  -1.918485e-03  -2.102644e-02  -1.271560e-01  -1.189991e-01  -5.586703e-02  -2.370529e-02  -4.848179e-02  5.337189e-02  6.631030e-02  -3.927423e-02  -2.054118e-02  1.097986e-02  -3.268356e-01  -2.349756e-01  5.594504e-02  2.600942e-02  -2.238563e-02  -1.120230e-02  5.135390e-03  4.158160e-01  1.294829e-01  -6.077086e-01  1.346916e-01  1.870469e-01  4.698621e-02  -2.334845e-02  2.882802e-02  1.308922e-01  1.561351e-02  2.006544e-02  1.024441e-01  8.143876e-02  1.357798e-01  -1.331048e-01  -9.734109e-02  -1.343918e-01  3.169907e-02  -1.572319e-01  -3.996873e-02  -2.754023e-02  -4.897238e-03  -8.063986e-02  1.521210e-01  -1.116224e-01  -5.625499e-03  -1.032899e-01  -5.793606e-02  -3.596400e-02  5.514774e-02  5.258985e-02  -8.223941e-02  -8.846735e-02  9.177855e-02  1.130961e-01  4.823684e-02  -3.185471e-02  7.321853e-02  -2.820495e-01  4.671131e-01  8.450774e-02  1.005652e-01  8.731870e-03  2.318326e-04  2.039501e-01  9.703235e-02  7.352751e-02  -5.974337e-02  1.813218e-01  -2.288162e-01  7.929207e-02  4.168012e-02  -1.597463e-01  1.508722e-01  7.542405e-02  -2.335266e-01  -1.160855e-01  5.251928e-02  1.157021e-01  1.401514e-01  -1.468030e-02  1.010086e-01  4.011392e-02  9.628914e-02  2.899274e-01  -1.074830e-01  7.454482e-02  -1.127215e-01  -7.483879e-02  5.299119e-01  1.551019e-02  -9.846906e-02  4.022152e-03  -3.367013e-01  -5.543902e-02  5.985905e-02  -3.855272e-02  -1.323093e-01  4.198343e-01  1.551121e-02  5.125232e-03  9.809755e-03  2.695207e-02  -1.130482e-01  5.234417e-02  9.621751e-02  1.185896e-02  1.905649e-01  -2.250027e-01  -6.351553e-02  2.979291e-01  1.813009e-01  -9.762955e-02  6.845815e-02  1.732274e-01  -4.571554e-02  -1.286751e-02  -1.277968e-01  -2.330964e-01  1.972091e-01  9.920267e-02  -4.709503e-02  -6.487340e-02  4.486390e-03  3.120294e-02  1.530410e-01  -1.055792e-01  -2.687451e-01  -1.021535e-01  1.743282e-01  4.113138e-02  -2.450942e-01  6.756809e-02  7.998263e-02  -1.070023e-01  -1.440930e-01  9.443511e-02  -1.053123e-01  -5.749726e-02  -1.549998e-02  1.916043e-01  -3.776489e-02  -1.243890e-01  -9.817618e-02  4.952586e-02  -1.159129e-01  5.783948e-02  5.003345e-03  -4.227983e-02  -4.493549e-02  -4.556123e-02  1.798784e-02  1.179274e-01  6.832889e-02  3.865983e-02  6.575773e-02  -1.176779e-01  -1.187165e-01  6.659088e-02  4.828035e-02  2.091346e-01  -5.277071e-02  -2.199778e-01  -4.308586e-02  5.566738e-02  -1.153992e-01  8.875500e-05  -1.233527e-01  6.187945e-02  5.713822e-02  9.858654e-03  4.466734e-03  1.327602e-01  1.325833e-01  -4.198849e-02  9.292176e-02  5.026364e-03  1.113492e-01  -6.963725e-02  2.487412e-01  -1.622506e-01  -1.586889e-01  -1.234912e-01  -3.188032e-02  -1.130419e-01  2.694178e-02  -1.833108e-01  -1.045061e-01  1.120403e-01  3.619648e-02  -1.326305e-01  -1.021569e-01  -1.507010e-01  1.469314e-01  -8.997636e-03  -1.370187e-01  1.432688e-01  -2.389620e-02  1.310168e-01  -1.632700e-01  1.482105e-01  1.764867e-01  -1.454950e-02  -7.533263e-02  1.683631e-01  1.091607e-01  -1.007106e-01  -3.958321e-02  -9.462128e-02  -1.886001e-02  9.252989e-02  1.194666e-01  -5.385556e-02  -1.234893e-01  -1.040750e-01  6.383381e-02  1.785723e-02  1.554792e-01  -3.922267e-02  6.069628e-02  4.760876e-02  3.659911e-01  -1.921166e-01  -6.375115e-02  -6.695952e-02  2.066751e-01  -8.953250e-03  6.239570e-02  2.318492e-01  1.184656e-01  -1.235676e-01  -1.208882e-01  -2.810482e-01  -1.128793e-01  4.048772e-02  6.623983e-02  6.522979e-02  -1.607067e-01  1.512377e-02  -5.165375e-02  5.239378e-02  -1.031409e-01  1.333243e-01  -1.201675e-02  1.460013e-01  -6.701724e-02  -5.280931e-03  -7.078798e-02  2.988335e-02  -1.227710e-01  -1.160407e-02  4.148405e-02  -3.749501e-02  -1.950668e-01  -3.422651e-02  -7.309129e-02  -3.270985e-02  -3.230384e-02  -8.451312e-02  -8.563600e-02  -1.040026e-01  6.370897e-02  2.645992e-02  5.657167e-02  1.084946e-01  -1.328128e-01  -7.033870e-02  8.131765e-02  1.500913e-02  1.383774e-01  2.479533e-02  -1.284676e-01  1.252404e-02  5.472577e-02  -7.424747e-02  8.614089e-02  1.046660e-01  8.488745e-02  -1.648603e-01  -1.159864e-01  2.101380e-01  3.279182e-02  9.406339e-03  1.824982e-01  4.384933e-02  -2.273114e-01  2.029041e-01  -1.433067e-01  -5.137329e-02  2.093532e-01  1.314548e-02  -6.806565e-02  -8.439834e-03  -5.200443e-02  -1.474970e-01  -5.459155e-02  2.828972e-03  -3.116891e-02  1.203990e-01  -1.465227e-01  -8.417559e-02  -1.354386e-01  1.088749e-01  5.993516e-02  6.440996e-02  -1.489438e-01  1.400450e-02  -4.218546e-02  1.043120e-01  -1.088710e-01  1.206279e-01  2.355420e-03  1.200955e-01  4.777903e-02  -1.196638e-01  8.031424e-02  -1.536440e-01  -1.221948e-02  -5.982650e-02  4.806702e-02  -7.282611e-02  9.475641e-02  5.825112e-02  1.452592e-01  -2.509870e-02  -3.991161e-02  -2.355304e-01  -3.384728e-02  3.839935e-02  9.895336e-02  -1.023449e-02  2.683647e-02  2.420836e-02  -1.740351e-04  -2.705471e-02  1.347073e-01  1.668962e-02  -6.930780e-01  1.450285e-01  -6.116134e-02  2.014858e-02  3.455724e-01  -4.284950e-03  -1.185033e-01  5.380487e-02  2.593794e-02  3.150624e-02  -9.139330e-02  2.148474e-02  -1.257261e-01  -2.025021e-01  1.482851e-01  -8.123183e-02  7.746864e-02  -1.671029e-01  -8.580022e-02  1.679608e-02  -9.019677e-02  3.361493e-02  1.982949e-02  -3.767747e-02  1.684631e-01  3.647068e-02  3.151197e-02  -3.371007e-02  1.110753e-01  1.109377e-01  -7.196216e-02  -1.020554e-01  1.687326e-01  7.880006e-02  1.155561e-01  -3.841113e-02  1.349734e-02  -1.315261e-01  4.236706e-02  3.287048e-02  -3.784522e-02  -1.365573e-01  1.111388e-01  -1.925841e-02  1.218750e-01  7.266378e-02  9.676011e-02  -2.397292e-02  2.649373e-02  1.705690e-01  4.241578e-02  4.033314e-02  6.591764e-02  -3.149131e-02  1.040185e-01  -1.601671e-01  -6.900218e-02  -4.376402e-02  -1.512511e-02  1.818137e-01  -3.680215e-01  -1.340532e-01  -1.950841e-01  1.009843e-01  4.408140e-03  5.781739e-02  1.268624e-01  -3.630256e-01  -6.961276e-02  1.581439e-01  -3.298278e-02  2.144904e-01  -7.354001e-03  -2.046976e-01  -8.127622e-03  1.794215e-02  -2.116322e-01  7.280956e-02  1.431879e-01  -6.644326e-02  -1.694505e-02  1.025053e-01  -1.138489e-01  7.453756e-02  1.478504e-01  -3.697843e-02  -3.126140e-03  -6.171825e-02  4.523649e-02  8.607088e-03  1.152508e-02  1.323632e-04  5.555903e-03  2.080809e-01  5.634594e-02  -3.708570e-01  -4.684503e-02  -3.615641e-02  -1.279682e-01  -1.144250e-02  -3.860992e-02  -5.623395e-02  6.096889e-02  -6.694266e-02  -6.316347e-02  8.555423e-02  2.860356e-01  5.941428e-02  1.031352e-01  5.232587e-02  4.709942e-02  -9.655134e-02  -1.251789e-01  -1.414153e-02  -2.768471e-02  6.496821e-02  -3.342832e-02  4.997801e-02  7.022124e-02  -1.021088e-02  2.149921e-01  -2.098858e-01  -1.369048e-01  9.379073e-02  -2.473629e-02  -1.617674e-01  1.769618e-01  -8.650123e-02  1.132531e-01  -7.226664e-03  1.060272e-01  1.179719e-01  -1.106459e-01  -1.958002e-02  1.856310e-01  6.845557e-02  -8.050252e-02  -1.034848e-01  5.828568e-02  -2.024617e-01  -8.303545e-02  -5.789865e-02  2.485609e-01  -7.201083e-02  -2.553191e-02  1.051927e-02  -2.367994e-01  4.329980e-03  -1.712745e-01  3.740484e-02  1.111667e-01  1.195863e-01  -4.448051e-03  -6.040970e-02  3.367401e-02  8.831133e-02  -7.019463e-02  1.192918e-01  -1.321934e-01  4.856687e-02  7.874740e-03  2.465963e-02  1.361164e-01  7.875645e-03  -1.207449e-01  1.885413e-02  -7.571864e-02  1.334500e-01  -1.466529e-01  7.567814e-02  1.064247e-02  -2.558036e-02  1.679501e-02  -1.342976e-01  7.228594e-02  5.023672e-02  -4.537521e-02  -1.422505e-01  -7.761006e-02  -1.414819e-01  -2.531732e-02  1.112222e-01  4.401945e-02  -6.378523e-02  6.766639e-02  1.518393e-01  1.135369e-01  4.523150e-01  -3.588232e-02  -9.686561e-02  -1.183230e-01  -2.582271e-01  5.891116e-02  -2.596353e-01  -9.570505e-02  -2.308270e-01  2.888101e-01  3.241094e-02  1.682150e-02  -3.774203e-02  -3.204222e-02  -6.268782e-02  -4.038327e-01  -5.607854e-02  2.799486e-01  -4.932916e-02  1.123173e-01  -1.493696e-02  -6.555876e-02  1.163726e-01  -4.939821e-01  -1.086474e-01  4.196671e-02  -9.914476e-02  3.166137e-02  1.818863e-01  -2.152616e-01  8.367872e-03  2.796057e-02  -1.696267e-02  1.411689e-01  6.089563e-02  4.970217e-02  4.380215e-02  -2.887702e-02  -2.152495e-01  -5.707217e-02  5.267681e-02  -1.559527e-01  -1.140738e-01  2.278712e-01  1.677203e-01  3.406887e-01  5.671699e-02  -8.279994e-02  1.738617e-01  -1.807212e-01  3.668648e-02  -1.862110e-01  -5.898107e-02  8.255614e-02  -1.237855e-03  2.011787e-01  7.413709e-03  -1.238937e-01  -1.443918e-01  -1.043906e-01  2.302243e-01  -1.730514e-02  -1.009177e-01  1.745955e-01  1.123786e-01  -1.204224e-01  -1.272977e-01  -3.853719e-02  -4.244310e-01  -3.364706e-03  -5.028097e-02  -1.264905e-01  -8.807193e-02  6.707507e-02  1.247146e-01  -9.582617e-02  -1.317772e-01  -1.450588e-01  6.874368e-02  -1.459539e-01  4.600755e-02  -9.701702e-02  -1.725516e-01  8.805399e-02  1.181992e-01  -4.648022e-02  1.395294e-01  1.723083e-01  2.298935e-02  -1.316662e-01  1.487671e-01  -4.865349e-02  -1.964062e-01  -1.170230e-01  -3.685743e-02  -4.335957e-02  7.991826e-02  -1.442011e-02  7.136804e-02  2.880542e-02  -1.137493e-01  7.322396e-02  2.604994e-02  1.435574e-01  1.491347e-01  -3.832809e-02  -1.433579e-01  4.543997e-02  9.814020e-02  -3.905851e-02  1.359900e-01  1.203712e-01  -1.212534e-01  1.013055e-01  -2.790748e-02  1.360071e-01  4.384314e-02  -2.140807e-01  9.733243e-02  -6.435172e-02  -2.328153e-01  4.171921e-02  1.036819e-01  6.116898e-02  -4.808574e-02  4.051241e-02  7.715780e-02  -3.302545e-02  -8.534072e-02  1.951295e-03  -6.649999e-02  9.779333e-02  -1.497097e-01  -2.840289e-02  -1.171435e-01  7.748838e-02  -1.086408e-01  1.258658e-01  -4.692058e-02  1.389793e-01  -7.138129e-02  1.079257e-01  -1.108855e-01  3.632387e-02  -8.555041e-02  -1.781226e-01  8.583770e-02  -8.189760e-03  -1.005015e-02  -4.174552e-02  -2.343768e-01  -5.737433e-02  6.911514e-02  -1.105445e-01  7.221932e-03  4.930983e-02  2.027388e-01  1.886147e-01  3.562527e-02  -2.575087e-02  3.017675e-02  5.030067e-02  1.776521e-01  8.305038e-02  -1.945358e-01  -1.517130e-01  -7.772155e-03  1.485390e-02  -1.098083e-01  1.299947e-01  1.571430e-01  -9.807182e-03  -6.330637e-02  7.626142e-02  1.030067e-01  7.373635e-02  3.221286e-03  2.233179e-02  -1.732676e-02  1.176797e-01  -1.641579e-02  2.625717e-02  -7.946523e-02  -3.349887e-02  -1.339367e-01  8.164670e-02  4.074541e-02  1.253528e-01  -4.234208e-02  4.958848e-02  -1.217238e-01  -1.216972e-01  1.243920e-01  6.935113e-02  -9.975214e-02  1.873194e-01  -1.027953e-01  -7.985838e-03  6.638209e-02  9.156219e-02  -2.570527e-02  1.250329e-01  4.682452e-02  -2.462933e-01  -1.403408e-01  -1.407270e-01  -2.170987e-01  -1.267437e-02  -3.214526e-02  -6.231539e-02  6.672993e-02  4.111448e-02  1.117210e-01  6.361952e-02  2.373746e-02  -1.601364e-01  -2.469296e-02  -1.408167e-01  9.374762e-03  -8.002625e-02  -7.736647e-02  -2.317606e-01  7.986527e-02  -2.031989e-01  -2.704682e-01  3.058933e-01  -2.006217e-02  -1.780114e-01  -1.075489e-02  -1.290450e-01  -1.008677e-01  1.804020e-01  -9.605849e-02  -1.691410e-01  6.767699e-02  2.203653e-01  -2.543739e-03  2.465311e-01  2.590308e-02  -1.212907e-01  9.992171e-02  3.798857e-02  -1.530305e-02  -5.609444e-02  -2.068842e-01  3.907251e-02  1.190800e-01  1.903624e-01  -2.355327e-01  6.034346e-02  3.679157e-02  -1.378698e-01  1.102241e-01  -1.257690e-01  9.048683e-03  1.328638e-01  3.861811e-03  6.007823e-02  -3.833691e-02  8.447265e-02  -5.334416e-02  -1.582768e-01  -7.381528e-02  1.135923e-01  -1.939957e-01  -4.430201e-02  -1.326442e-01  -8.961552e-02  1.249550e-01  1.518702e-01  6.030714e-02  5.123143e-02  1.168529e-01  -9.967554e-02  -1.606578e-01  6.287733e-02  -1.179540e-01  -1.604534e-01  -5.783793e-02  1.364802e-01  6.086667e-02  8.229745e-03  -1.296061e-02  8.491216e-02  -3.333649e-02  7.381551e-02  -1.213364e-01  1.987357e-01  7.493974e-02  5.230847e-02  -1.684612e-01  -9.385005e-03  1.295953e-01  2.939286e-02  -3.998877e-02  8.992004e-02  -2.104638e-02  9.669549e-02  -6.268134e-02  -5.263394e-02  -5.835701e-02  6.475051e-02  -8.404474e-02  -1.020586e-02  4.044979e-03  -5.596076e-02  -8.141018e-02  -5.198549e-02  9.538186e-02  1.210949e-02  6.991134e-02  6.548593e-02  4.632374e-02  -1.186446e-01  7.354355e-02  -1.529618e-01  2.019062e-02  -2.191032e-01  -1.468364e-01  5.987831e-02  -4.995411e-02  -3.905928e-02  -4.434474e-02  3.918241e-02  9.188662e-02  -8.483898e-02  -1.300785e-01  4.439168e-02  -3.834886e-01  2.007103e-02  -3.081474e-02  -2.418500e-01  -9.957245e-02  -1.619757e-02  -1.884632e-02  4.880671e-02  -2.871276e-02  1.992394e-01  1.493327e-01  -1.095567e-01  -1.156484e-01  -3.054201e-02  1.328020e-02  5.088038e-02  4.100230e-03  1.077845e-01  -1.222039e-01  -1.036048e-01  -1.889727e-01  7.663080e-02  1.561369e-01  -4.097658e-02  2.048571e-02  6.178469e-02  -8.491151e-03  1.190240e-01  1.054745e-01  2.829571e-02  -1.643717e-01  8.187057e-02  1.182445e-01  -2.827747e-01  2.756581e-01  1.192144e-01  -1.721884e-01  -1.396903e-01  2.034395e-01  2.247177e-01  1.832433e-02  -1.929396e-01  1.776666e-01  -1.059230e-01  -9.538604e-02  -5.185174e-02  -1.207858e-01  -1.390789e-02  -6.220134e-02  8.052883e-02  6.398562e-02  -1.144646e-01  -1.119099e-01  -7.746377e-02  -1.668011e-01  -1.148725e-01  8.915336e-02  -6.970649e-03  1.539664e-01  -1.939153e-01  -1.675187e-01  -9.306229e-02  -8.856013e-02  8.235622e-02  1.223027e-01  -1.618806e-01  -1.669965e-01  7.347970e-04  8.163122e-02  1.302007e-01  5.598360e-02  1.479574e-01  7.037848e-02  -2.080609e-01  1.232939e-01  -1.380813e-01  4.694969e-02  -1.595812e-01  5.775292e-02  4.665431e-02  -1.517638e-01  -9.374638e-03  -1.783224e-02  -7.993013e-02  8.219837e-02  1.600909e-01  -4.932332e-02  2.646074e-02  1.037425e-01  -3.334633e-02  -3.862695e-01  -5.314043e-01  -5.613987e-01  1.470194e-01  8.542099e-02  2.863905e-02  3.415948e-01  -5.809734e-02  1.646076e-01  1.084482e-01  5.381605e-02  -7.703646e-02  -1.504407e-01  -9.017824e-02  5.535389e-02  9.297271e-02  -2.242949e-02  -1.836102e-01  3.816649e-03  2.558240e-02  6.012665e-03  1.080645e-01  -1.293695e-03  2.563655e-02  2.654338e-02  -4.260399e-01  -1.610318e-01  1.087683e-01  1.803767e-01  -2.378284e-02  -4.323478e-02  -4.017318e-02  1.532715e-01  4.722854e-02  1.006496e-01  -2.871661e-02  4.405548e-02  1.344730e-01  -1.758318e-01  5.243643e-02  -5.768223e-01  1.500378e-01  -2.416130e-01  1.622676e-02  -8.313011e-02  6.471334e-02  -1.765692e-01  -4.268563e-01  1.323907e-02  1.310361e-01  2.267122e-02  3.234973e-01  6.293383e-02  -1.695469e-02  -2.615540e-02  2.112722e-01  -3.331521e-01  -2.916195e-02  -3.230370e-02  5.331621e-02  -1.397661e-01  1.606920e-01  -7.920478e-02  1.054635e-01  1.094626e-01  -9.449680e-02  1.427618e-01  8.306161e-03  1.422365e-03  7.508890e-02  -6.397190e-02  8.247155e-02  1.382292e-01  -1.272762e-01  -5.081792e-03  -3.078095e-02  3.386419e-02  1.406679e-02  1.792689e-02  3.461963e-03  -3.294916e-02  3.223760e-02  3.771599e-03  1.253800e-01  1.242855e-01  -3.673269e-01  2.276109e-01  9.975015e-02  9.333249e-02  -5.237275e-02  -1.001734e-02  -9.338574e-02  -1.272559e-01  3.610964e-03  1.451385e-01  1.721288e-02  -3.134329e-02  -2.849311e-04  -1.462853e-01  -2.252517e-02  1.321006e-01  -3.115021e-02  -1.078213e-01  -6.773061e-02  -8.293962e-02  -3.032747e-02  -1.395396e-01  -1.731251e-01  -1.094560e-01  1.871524e-01  1.270259e-01  -2.031632e-01  -1.081251e-01  -1.490179e-01  -1.776561e-01  2.027466e-02  -6.709775e-02  1.436866e-01  -3.163495e-02  1.106112e-01  -6.561963e-02  -5.929499e-02  3.379557e-01  -2.044248e-02  1.710334e-03  -1.251367e-02  -1.043415e-01  -6.181291e-02  -5.652430e-02  -6.720108e-04  -4.545037e-02  1.746501e-01  -8.202103e-02  -8.565972e-02  -2.185961e-01  -2.144829e-01  -2.904346e-02  -1.061899e-01  -3.941792e-02  1.378150e-01  1.050849e-03  1.246273e-01  -4.114239e-02  1.837496e-01  9.684301e-02  -2.152841e-01  -2.484393e-01  -1.167600e-01  -5.169123e-02  7.257086e-02  -4.883584e-03  1.656412e-01  4.591016e-02  8.652612e-02  1.575015e-01  -9.380092e-02  -4.099985e-03  1.096430e-01  2.182314e-02  2.057134e-01  -1.168708e-01  -1.333852e-03  3.571751e-02  8.912035e-02  -2.045595e-01  4.719822e-02  -1.511141e-02  -1.089894e-01  2.837888e-02  6.204319e-02  -1.839866e-01  1.182466e-01  1.503427e-01  -8.732017e-02  4.744942e-02  2.661956e-02  -3.600723e-02  -9.667177e-02  1.763006e-02  -3.774092e-02  -2.667612e-02  -3.056770e-02  1.043841e-01  1.880787e-02  -8.413515e-02  -2.904006e-02  -6.560008e-02  -2.472355e-02  2.369111e-01  4.298117e-02  -8.434725e-01  -3.971156e-03  -5.543042e-03  1.200643e-01  5.139384e-03  1.128478e-02  -3.851210e-01  -1.734582e-01  1.451822e-01  -2.032142e-02  -2.021431e-02  9.119742e-02  -2.222427e-03  3.503509e-01  -1.279263e-01  -5.014006e-01  -1.032614e-01  5.609605e-02  -5.994517e-02  3.890872e-02  -9.585126e-02  7.793084e-02  1.188902e-01  3.082960e-02  -2.933852e-02  3.284384e-02  -8.384327e-03  9.328498e-03  1.125073e-01  -1.255686e-01  1.234049e-01  8.449773e-02  2.198058e-02  8.038072e-02  1.024625e-01  -1.771204e-01  1.571223e-01  7.546781e-02  -2.871767e-01  8.623974e-03  1.581827e-01  -9.533595e-02  1.420989e-01  5.031280e-02  -5.490789e-02  4.654494e-02  -1.667860e-01  8.276125e-02  1.010225e-01  -1.426815e-01  -1.794573e-02  -2.826943e-03  -2.476611e-01  -9.418544e-03  1.496075e-01  -6.187749e-02  1.193213e-02  3.306217e-02  4.931691e-02  1.267576e-01  -2.063928e-01  4.435219e-02  1.187459e-01  2.646382e-02  -6.394538e-02  -7.920817e-02  1.688651e-01  2.164612e-01  -1.527968e-01  -2.222993e-02  3.066817e-03  -9.283817e-02  -3.598515e-02  -2.656331e-01  6.605066e-03  -2.470347e-01  -1.176166e-02  3.511102e-02  -1.120570e-01  6.153536e-02  -1.080655e-01  -7.857127e-02  -8.434585e-02  8.590788e-02  5.827540e-02  1.514458e-01  -7.606424e-02  3.428123e-02  -7.584315e-02  -8.137306e-03  -8.277146e-02  1.483017e-02  -1.250382e-01  -1.266099e-01  1.112790e-01  9.067047e-02  6.914932e-02  5.650685e-02  8.273055e-02  -9.291317e-02  -3.295333e-03  -1.042463e-02  1.756869e-02  -2.698647e-01  5.638321e-03  -4.033059e-01  4.480727e-02  -3.897701e-02  -5.257356e-02  -1.050794e-01  -6.603909e-02  -9.932866e-03  -1.691502e-02  1.937943e-03  -9.576028e-03  -5.304617e-02  -1.562971e-01  -1.336740e-01  -3.895097e-02  -1.053810e-01  9.844836e-02  -3.456258e-02  1.307771e-01  2.001333e-01  -1.361712e-01  -5.107597e-02  5.251049e-02  1.787251e-01  -1.138756e-01  -1.546794e-01  -1.556725e-01  2.552148e-01  2.265124e-01  -9.588953e-04  3.236432e-01  -1.724251e-01  -1.315126e-01  -4.302645e-02  -1.009451e-01  1.077486e-01  4.424749e-02  1.216968e-01  -2.375928e-01  -1.181870e-01  4.853638e-02  7.979097e-02  -7.329279e-02  -9.834678e-02  -2.513283e-01  7.689205e-02  4.451672e-02  -2.865517e-02  9.027813e-02  -1.174660e-01  7.644308e-02  1.390445e-01  -5.520055e-02  1.553478e-01  1.089644e-02  1.630870e-02  1.215900e-02  -3.004705e-02  2.591761e-02  1.258870e-01  -9.697900e-02  -3.342905e-02  -1.599698e-01  8.283997e-02  4.612267e-02  -2.993855e-02  -6.336670e-02  -2.437120e-02  -1.453562e-01  1.143976e-01  -3.915583e-02  -1.209215e-01  1.818515e-01  -1.386337e-02  -5.950018e-02  -7.220004e-02  3.468534e-02  1.324996e-01  -6.453097e-02  -1.663993e-01  1.239918e-01  -1.916394e-01  2.297045e-02  2.231594e-02  -2.311975e-01  -1.703869e-01  -3.711943e-02  6.250459e-02  1.149046e-02  2.600194e-02  -1.617653e-02  5.691858e-02  -1.297089e-01  -1.560843e-01  8.787320e-02  -1.158301e-02  1.276640e-01  1.551083e-02  -7.500798e-02  -9.304695e-03  -8.670569e-02  1.053908e-02  1.821256e-01  -1.875792e-02  -2.148988e-01  -1.091278e-01  -2.329331e-01  -5.565954e-02  9.857411e-02  1.826585e-01  2.110511e-02  -9.310833e-03  1.076110e-01  -5.090272e-02  1.111260e-01  -5.790914e-02  -6.093574e-02  8.042330e-02  -1.297079e-01  -7.120203e-02  -7.122387e-03  6.364635e-03  1.709930e-01  -1.155268e-01  -1.143315e-01  1.141338e-01  6.742170e-02  -1.008919e-02  -1.099634e-01  -1.530065e-02  6.502759e-02  1.456757e-02  1.049597e-01  -6.179865e-02  -1.585026e-01  -4.631189e-02  -4.574500e-02  3.086445e-04  -2.150936e-02  1.048308e-01  -5.040709e-02  1.100882e-02  -3.494992e-02  -1.946908e-01  -9.455971e-02  9.211638e-02  2.336786e-01  1.292907e-01  9.314307e-02  -1.531719e-01  1.791240e-01  5.494794e-02  1.399467e-01  -1.782015e-01  -5.051191e-03  -1.209429e-01  -1.627746e-01  -8.387449e-02  -1.396108e-01  -6.493253e-02  -9.904268e-02  -7.478603e-02  1.580472e-01  1.209426e-01  5.369189e-02  -1.367574e-01  2.211392e-02  -5.228662e-02  -2.289965e-02  -2.011673e-01  -9.058011e-03  -3.002415e-01  1.117678e-01  -8.764853e-02  -4.651867e-01  -3.163488e-02  1.898285e-02  -1.420248e-01  6.329698e-02  9.525213e-02  1.501445e-01  1.828380e-01  -1.828454e-01  -1.485797e-01  -4.920391e-02  -8.654889e-03  9.915636e-02  1.060926e-01  -6.878675e-02  2.011838e-01  -5.207281e-02  -1.442480e-02  -1.394109e-01  -5.313054e-02  -1.098712e-01  2.391558e-02  -5.840684e-02  -1.294563e-01  3.681874e-02  -1.130450e-01  2.198047e-01  6.712723e-02  -2.738430e-01  -3.173671e-02  1.377812e-02  1.035868e-01  -1.538055e-02  5.256014e-02  2.413464e-01  1.440173e-01  -3.529385e-02  -3.504767e-02  1.507438e-01  4.513964e-04  9.696928e-02  5.911469e-02  -4.603840e-02  -7.335439e-02  9.828392e-02  4.351570e-02  -9.666251e-02  3.290132e-02  9.235980e-03  -6.457163e-02  1.326903e-01  -7.707114e-03  -1.922242e-01  -1.519392e-01  -5.680463e-02  9.512130e-02  7.645623e-03  -9.087507e-02  1.157330e-01  7.426375e-02  9.627605e-02  -9.936860e-02  1.481905e-01  7.227524e-02  8.510821e-02  1.179094e-01  1.113510e-02  -1.245180e-01  1.136271e-01  1.299079e-01  -7.180201e-02  -3.517460e-02  -1.879717e-01  -8.715208e-02  -1.017448e-01  2.535962e-02  -1.782008e-02  -2.994828e-02  -1.488428e-01  9.807918e-02  -9.217031e-02  -1.968476e-02  -9.065817e-03  -7.735797e-02  -1.986311e-02  3.406513e-02  -2.461036e-02  -1.240212e-01  -6.194184e-02  4.484963e-02  -7.600006e-03  -1.421339e-01  -1.441809e-01  1.145520e-01  1.235633e-01  -1.194558e-01  5.200559e-02  1.587879e-01  -5.634045e-02  -7.666154e-02  -1.483790e-01  3.694372e-02  -8.789364e-02  -3.113792e-01  2.730505e-01  2.729284e-01  -1.341961e-01  -8.518758e-03  -2.255232e-01  5.669532e-02  3.938529e-01  1.722399e-02  -4.261906e-01  2.308397e-01  8.053885e-02  1.183542e-02  2.309139e-01  -5.215210e-02  -1.206143e-01  -1.628467e-01  2.169583e-01  -1.089398e-01  3.275932e-02  -2.711593e-02  6.650858e-02  3.217181e-02  -5.805311e-02  -2.184414e-01  -9.365153e-02  1.727659e-01  5.571173e-02  2.364999e-01  2.511271e-02  -2.260289e-01  7.603224e-02  5.681321e-02  -1.379450e-01  1.395794e-01  -1.292854e-01  7.711645e-02  2.380126e-01  1.509532e-01  1.727032e-01  1.528919e-01  -6.270018e-03  -1.168285e-01  -1.097912e-01  3.889225e-02  5.934697e-02  1.330708e-01  -8.310521e-02  1.530842e-02  4.574432e-02  -9.219300e-02  8.938747e-03  -5.538638e-02  -1.120976e-01  -1.520328e-02  -2.195409e-02  7.351539e-02  -1.490215e-01  -1.495965e-02  1.233758e-02  1.027991e-01  1.402870e-01  -1.246453e-01  7.853428e-02  6.705758e-02  -1.316433e-02  -1.109315e-01  6.619800e-02  1.048490e-01  -1.021207e-01  -3.595092e-02  1.616352e-01  1.009383e-01  1.228142e-01  -9.555876e-03  -2.853821e-02  -1.585780e-01  3.609569e-02  5.047967e-02  3.881510e-02  1.623699e-01  -9.896608e-02  9.825227e-02  -6.847443e-02  -1.299476e-01  -9.880207e-02  -1.468554e-01  4.769798e-02  8.833526e-02  6.866533e-02  8.100838e-02  2.885069e-02  -2.210630e-01  -1.093392e-01  1.419920e-01  -1.229858e-01  1.346250e-01  -2.105764e-02  -6.595708e-02  5.065490e-02  5.489723e-02  -2.114572e-02  4.046334e-02  -2.115687e-01  -6.933369e-02  1.120582e-01  2.305982e-01  1.063243e-01  -1.898440e-01  -1.227743e-01  1.753032e-01  2.335526e-01  -1.204467e-01  7.792044e-02  4.506128e-02  -7.360734e-02  5.715712e-02  5.050055e-02  -1.134202e-01  -1.875441e-02  9.073760e-02  1.008180e-01  -1.105250e-01  -8.436197e-02  7.564068e-02  8.880679e-02  1.797640e-01  -6.370263e-02  1.642100e-01  1.013684e-01  -1.352916e-01  -1.635939e-02  7.560835e-02  -1.308041e-01  -1.562696e-01  1.357916e-01  3.298552e-02  1.103246e-01  1.042494e-02  1.383094e-01  6.651095e-02  1.355344e-01  -1.174936e-02  4.834343e-02  9.442282e-02  -2.450283e-02  5.960783e-02  -3.668019e-02  -4.053096e-02  4.321845e-02  -5.933171e-02  -4.096666e-01  6.791271e-02  5.940861e-02  -1.444750e-01  1.659199e-01  -1.300334e-02  1.003314e-02  8.933046e-02  -2.611900e-01  -4.684857e-02  1.674725e-01  -3.861610e-02  7.011969e-02  8.675888e-03  -2.472482e-01  1.094804e-01  1.659382e-01  -1.267782e-01  -2.207897e-02  -1.953372e-01  -2.703338e-03  2.757881e-01  1.676639e-01  -3.269118e-01  2.118507e-01  9.317584e-02  3.730362e-02  -1.533451e-01  -8.833185e-02  -2.463549e-01  8.258570e-02  -5.759427e-02  2.977050e-02  -1.282220e-02  -5.560074e-02  -1.048461e-01  1.653086e-02  -1.592088e-01  -1.532063e-01  -1.314924e-01  1.278190e-01  9.106298e-02  -4.481370e-02  -1.139416e-01  1.397249e-01  6.156021e-02  -1.846939e-01  -5.701104e-02  -6.773696e-02  -5.712144e-02  1.998423e-01  3.216122e-02  9.240098e-02  4.540372e-02  -1.376749e-01  4.769574e-02  -7.741851e-02  1.146879e-01  -2.464947e-02  1.612572e-02  1.288122e-01  1.010453e-01  1.154176e-01  1.423645e-01  -5.173973e-02  5.444624e-02  -1.157695e-01  -5.708116e-02  4.462559e-02  1.291479e-01  1.739866e-02  -1.295236e-01  -3.193449e-02  -6.345106e-02  6.906393e-02  1.611273e-01  -5.826218e-02  -5.341575e-02  3.328075e-03  -1.576012e-02  -1.013499e-02  8.135252e-02  3.291428e-02  -6.707376e-01  1.196615e-01  -1.094997e-01  5.538763e-02  2.158746e-02  -1.036719e-01  1.590873e-01  -1.342476e-01  -1.316072e-01  4.983918e-02  -7.273722e-02  5.358299e-02  2.910599e-02  1.446992e-01  2.387069e-02  -2.239740e-02  1.691637e-01  -1.418343e-01  -8.960644e-02  1.093745e-01  1.511152e-01  -8.344096e-02  8.304586e-02  -2.318458e-02  -6.186336e-02  1.451795e-01  5.754475e-03  6.361054e-02  -7.007445e-02  7.351034e-02  -1.118280e-01  -8.553571e-02  2.433155e-02  1.460451e-02  -9.210892e-02  1.652959e-01  -1.872004e-01  3.136363e-02  -6.406911e-02  1.204736e-01  -1.386532e-01  2.282730e-02  1.591876e-01  -2.846487e-01  -5.121211e-02  -1.577649e-01  1.327233e-02  1.607853e-03  1.944262e-01  -3.251998e-02  -1.225806e-01  1.817284e-02  -1.237505e-02  -1.527697e-01  9.628326e-02  -6.487583e-02  -4.664902e-02  9.542976e-02  2.618727e-02  -1.950990e-01  -1.719232e-02  1.310495e-01  3.462413e-02  4.008599e-02  -2.672088e-02  -2.509865e-04  1.251246e-01  -2.621253e-02  -8.009272e-02  9.588314e-02  -1.229358e-01  8.308089e-02  -9.341818e-02  9.991657e-02  1.077040e-01  1.370991e-01  -4.845789e-02  7.441825e-02  
      </Weights>
      <Biases Rows="256" Columns="1">
        -6.159100e-02  -1.694980e-01  -5.536599e-03  -1.691273e-01  -4.654369e-02  2.522194e-02  -1.119498e-02  -6.626824e-03  -4.743762e-02  1.230134e-01  -1.359679e-01  1.162755e-01  7.062825e-02  -4.054486e-02  8.367123e-02  6.289881e-02  2.070094e-02  -8.237937e-02  1.056305e-02  9.244712e-02  -1.183951e-02  -1.541780e-02  -2.677906e-01  -7.511376e-02  -8.163528e-03  -2.926410e-02  -7.386523e-02  -1.508263e-01  -6.754880e-02  -5.320193e-03  -1.009154e-02  -8.570129e-02  2.741844e-02  1.089129e-02  -1.200778e-02  -1.839407e-01  1.903911e-02  -2.910560e-02  -7.967086e-03  -1.205853e-01  -1.401653e-01  4.422046e-03  3.044133e-02  2.022598e-02  -9.023552e-02  1.407478e-03  1.323562e-02  -1.543442e-02  -5.640256e-02  2.575354e-02  -1.430205e-01  -2.344310e-05  -8.918842e-02  -3.879686e-02  8.684845e-03  1.855072e-02  2.016540e-01  -5.242537e-02  -8.371238e-03  -2.546588e-01  -3.320570e-01  -4.428382e-03  -3.545548e-02  1.704514e-02  -3.142309e-02  -3.484973e-02  -7.809333e-03  9.143062e-03  6.057391e-03  -8.129001e-02  -1.228127e-03  -5.340968e-02  1.086700e-02  -1.689049e-02  -9.528084e-03  1.359687e-01  1.637108e-01  5.916908e-02  -1.166595e-03  -1.468179e-01  -8.312686e-02  -2.091814e-01  -2.157114e-02  1.232305e-01  8.895692e-03  -8.495010e-02  8.081935e-02  -8.918898e-02  -2.630941e-02  2.327299e-04  2.520778e-01  -3.249999e-01  1.191444e-03  -1.223323e-02  -8.326055e-03  8.922607e-03  9.241848e-02  2.803437e-02  -1.034728e-01  -1.117723e-02  -2.956994e-02  -9.855340e-02  7.298942e-03  7.328857e-02  -2.199643e-02  -1.544040e-01  -1.322065e-03  -6.538838e-02  -1.047153e-02  -4.948131e-01  -4.110250e-02  1.621901e-02  -1.340634e-01  2.215832e-02  -6.291774e-02  -5.972490e-02  -1.916262e-02  -7.218267e-02  -1.465008e-02  9.109338e-02  -7.263757e-02  -1.989835e-01  -5.061584e-02  -6.301419e-01  -5.676937e-01  1.389897e-02  1.482754e-01  1.620272e-02  3.855154e-02  -3.815303e-01  -4.196631e-02  7.221920e-03  -4.014212e-02  3.535399e-04  -2.529440e-02  -5.324405e-01  -6.972365e-03  -2.437506e-02  -3.055123e-02  2.868037e-02  -7.090458e-02  -7.676956e-02  -1.096436e-01  -5.488325e-02  -5.787363e-02  2.115261e-02  -1.114329e-01  1.998771e-03  -2.579058e-02  -1.126772e-01  -1.194544e-02  1.663437e-02  -3.405152e-02  4.451064e-02  3.934010e-02  1.438740e-02  -4.068779e-01  -1.208708e-01  1.694166e-02  2.549256e-02  -1.194394e-01  -1.087033e-01  -7.703006e-03  1.333701e-01  -9.382169e-03  -4.511075e-02  -4.354938e-02  -1.310690e-02  1.485064e-02  -3.159356e-01  -3.380406e-01  -1.291560e-01  -1.127684e-01  -2.773483e-01  3.127829e-02  -3.145080e-02  -1.560124e-02  -1.227078e-01  -1.435941e-02  -6.659438e-03  1.671826e-03  -7.989658e-04  -2.069527e-01  1.393764e-02  -1.298155e-02  -5.987200e-02  -7.600497e-03  -7.563630e-02  7.802622e-02  -3.234200e-02  -2.139092e-03  1.595455e-01  5.742330e-02  1.797429e-01  -9.691359e-02  -1.179999e-02  1.535064e-02  1.068965e-01  -2.601241e-01  -2.733799e-01  -4.099154e-02  -1.665328e-02  -1.860383e-01  6.369448e-03  -3.728288e-02  -9.309784e-02  -6.035824e-02  -5.169183e-02  -4.434576e-02  -5.355577e-01  -3.652241e-01  -2.954164e-02  1.365877e-01  -7.630763e-02  -2.146165e-01  -1.869098e-02  -2.795374e-01  2.444630e-03  1.044643e-01  -1.431593e-02  -6.206136e-02  2.102805e-02  3.996135e-02  -1.196966e-01  1.641134e-02  -1.075362e-01  1.368916e-01  2.080500e-02  1.242424e-01  -4.574156e-03  -3.803555e-02  -3.427340e-02  -1.655509e-02  -1.667516e-02  2.307770e-02  -7.201042e-02  -9.941256e-02  -3.011754e-02  -9.136401e-03  -1.063502e-02  -4.549991e-02  3.486293e-02  -1.065065e-02  2.392912e-02  6.967454e-03  -1.032150e-01  -1.690825e-01  -1.441609e-01  2.649430e-02  -3.559761e-02  -4.352905e-01  -2.037747e-02  -1.100245e-02  -1.005911e-01  9.912597e-02  -1.405757e-02  
      </Biases>
    </DenseLayer>
    <DenseLayer Width="1" ActivationFunction="0">
      <Weights Rows="1" Columns="256">
        -1.057173e-01  -3.798659e-01  -9.606329e-02  -3.639849e-01  4.392380e-02  -1.643996e-01  -2.425260e-01  -1.275350e-01  -3.279420e-01  3.271091e-01  -5.689247e-01  3.679654e-01  3.034349e-01  -2.086206e-01  4.965342e-01  2.299486e-01  -2.846341e-01  -4.886367e-01  -1.015263e-01  4.709811e-01  -1.060997e-01  -6.418528e-02  -4.936951e-01  -3.696549e-01  -1.506403e-01  -4.270540e-01  -2.239229e-01  -4.463648e-01  -2.389677e-01  -2.387719e-01  2.215794e-01  -7.473789e-01  -2.843995e-01  2.620062e-02  -1.303094e-01  -5.223452e-01  -5.352285e-01  -4.968904e-02  2.216437e-01  -2.646294e-01  -2.654597e-01  -3.876867e-01  -3.252524e-01  -1.356175e-01  -2.393205e-01  -2.632365e-01  1.350348e-01  9.954095e-02  -2.944214e-02  2.371150e-01  -3.786970e-01  -1.889348e-01  -2.980597e-01  3.556003e-01  1.331501e-01  -2.381739e-01  2.648149e-01  -2.975091e-01  -1.213951e-01  -3.914672e-01  -6.167244e-01  -7.028285e-02  1.316807e-01  1.247842e-01  2.850132e-01  -6.503891e-01  1.619467e-01  1.289143e-02  -5.208992e-02  -2.173022e-01  1.383133e-01  -1.413523e-01  7.097652e-02  1.577933e-01  -3.215475e-02  2.905767e-01  4.272971e-01  3.827545e-01  -1.426015e-01  -3.621112e-01  -1.961131e-01  -5.124271e-01  -4.521290e-01  2.526970e-01  8.901983e-02  -4.792101e-01  2.605830e-01  -6.915675e-01  -4.640061e-02  7.364914e-02  4.228643e-01  -5.505808e-01  -6.676268e-02  -1.103113e-01  -2.508944e-01  -1.004701e-01  -6.614917e-01  -1.739562e-01  -5.928822e-01  2.107138e-01  -1.179462e-01  -4.602137e-01  -8.605754e-02  3.267299e-01  2.363076e-01  -6.902084e-01  7.069231e-02  -4.302471e-01  -4.231108e-02  -7.929130e-01  1.456472e-01  7.311875e-02  -2.210412e-01  -2.638932e-01  1.181895e-01  8.243839e-03  -3.038650e-01  -3.151263e-01  -2.694417e-01  1.429959e-01  -2.750950e-01  -5.549619e-01  -2.681015e-01  -1.089101e+00  -9.793680e-01  -1.347104e-01  4.469423e-01  -7.015727e-02  4.339163e-01  -6.853721e-01  -1.008751e-01  2.150312e-01  -2.581399e-02  2.274940e-01  6.834053e-02  -9.474044e-01  -1.123316e-01  9.095440e-02  -5.947232e-01  3.978245e-01  -6.909822e-01  -4.497496e-01  -4.263775e-01  -2.119299e-01  -2.606780e-02  2.365461e-01  -3.625532e-01  2.289016e-01  1.275994e-02  -5.543758e-01  1.222018e-01  -3.504569e-02  1.830690e-01  3.733830e-01  1.685077e-01  4.484429e-02  -8.086304e-01  -3.864245e-01  1.341364e-01  -6.231327e-02  -4.233153e-01  -5.152206e-01  1.332566e-01  4.909542e-01  -2.096109e-01  2.055195e-01  -3.324400e-01  1.113723e-01  2.059262e-02  -7.051934e-01  -6.683623e-01  -2.882781e-01  -5.574818e-01  -5.603854e-01  2.298155e-01  -2.413905e-01  1.109747e-01  -2.480592e-01  -2.020205e-01  -2.942537e-01  -2.492592e-01  -6.506743e-02  -3.744645e-01  1.971602e-01  -5.672083e-01  -3.905106e-01  -1.693259e-01  -2.706604e-01  1.977043e-01  -1.222498e-01  1.904522e-01  4.725282e-01  2.060780e-01  5.803699e-01  -1.961650e-01  -3.767088e-01  -3.066027e-01  -8.764026e-01  -4.729807e-01  -6.625317e-01  -5.943881e-01  1.718601e-02  -3.697284e-01  -9.220066e-02  -3.151271e-01  -3.044938e-01  -4.168976e-01  2.202219e-01  -2.004843e-01  -1.001435e+00  -8.084484e-01  5.996124e-02  3.573632e-01  -2.059593e-01  -4.264092e-01  -6.940764e-03  -5.227132e-01  1.763992e-01  5.476180e-01  -3.226932e-01  1.024758e-01  1.721071e-01  2.981906e-01  -2.959360e-01  2.309166e-01  -2.069172e-01  3.602075e-01  -1.689827e-01  6.191655e-01  1.613556e-01  -2.959790e-01  -1.882512e-01  3.462638e-02  2.047035e-01  -1.633869e-01  -8.024426e-01  -3.482010e-01  -4.121971e-01  9.803392e-02  1.362316e-01  -2.035654e-01  2.281205e-01  -3.561671e-01  1.424046e-01  8.586194e-02  -4.795430e-01  -5.669790e-01  -2.575721e-01  2.981888e-01  -1.347620e-01  -8.005509e-01  1.904809e-01  -1.757744e-01  -3.084805e-01  3.340825e-01  -1.066564e-02  
      </Weights>
      <Biases Rows="1" Columns="1">
        4.865391e-01  
      </Biases>
    </DenseLayer>
  </Weights>
</MethodSetup>
